{"events":[{"created":1377865761000,"id":"137486532","name":"GDG Budapest September","rsvp_limit":40,"date_in_series_pattern":false,"status":"past","time":1379955600000,"local_date":"2013-09-23","local_time":"19:00","updated":1380012282000,"utc_offset":7200000,"waitlist_count":0,"yes_rsvp_count":40,"venue":{"id":15347352,"name":"Cloudoffice 1","lat":47.52043914794922,"lon":19.06551170349121,"repinned":false,"address_1":"Váci út 19, 1st floor (entrance form Lőportár St.)","address_2":"Panoráma Irodaház","city":"Budapest","country":"hu","localized_country_name":"Hungary"},"group":{"created":1356866254000,"name":"GDG Budapest","id":6397942,"join_mode":"open","lat":47.5099983215332,"lon":19.079999923706055,"urlname":"GDG-Budapest","who":"GDG Budapester","localized_location":"Budapest, Hungary","state":"","country":"hu","region":"en_US","timezone":"Europe/Budapest"},"link":"https://www.meetup.com/GDG-Budapest/events/137486532/","description":"<p>First GDG Budapest meetup!<br/>We try to cover different topics, even loosely connected to Google.<br/>Each presentation takes 10-15 minutes.</p> <p>Please register on this page and follow us on Google Plus: <a href=\"https://plus.google.com/109554147114014091559/posts\" class=\"linkified\">https://plus.google.com/109554147114014091559/posts</a></p> <p>Topics:<br/>1.) Security Fundamentals in Software Develepment (Ethical Hacking?)<br/>György Kollár, CISSP (<a href=\"https://plus.google.com/107759858376123872275/posts\" class=\"linkified\">https://plus.google.com/107759858376123872275/posts</a>)</p> <p>2.) Google Pagespeed modul, experiences.<br/>Open-source webserver module to speed up websites.<br/>Szabolcs Sándor (<a href=\"https://plus.google.com/112373405071039337118/posts\" class=\"linkified\">https://plus.google.com/112373405071039337118/posts</a>)</p> <p>3.) Google App Engine, First Experiences with Java<br/>Róber Vincze (<a href=\"https://plus.google.com/115843439460756933785/posts\" class=\"linkified\">https://plus.google.com/115843439460756933785/posts</a>)</p> <p>4.) Google Tag Manager usage in Marketing<br/>István Maczkó (<a href=\"https://plus.google.com/104571352002510381880/posts\" class=\"linkified\">https://plus.google.com/104571352002510381880/posts</a>)</p> <p>Language of the meeting: Hungarian.</p> ","visibility":"public"},{"created":1381933698000,"id":"145854122","name":"GDG Budapest October","rsvp_limit":40,"date_in_series_pattern":false,"status":"past","time":1382983200000,"local_date":"2013-10-28","local_time":"19:00","updated":1383129365000,"utc_offset":3600000,"waitlist_count":0,"yes_rsvp_count":18,"venue":{"id":15347352,"name":"Cloudoffice 1","lat":47.52043914794922,"lon":19.06551170349121,"repinned":false,"address_1":"Váci út 19, 1st floor (entrance form Lőportár St.)","address_2":"Panoráma Irodaház","city":"Budapest","country":"hu","localized_country_name":"Hungary"},"group":{"created":1356866254000,"name":"GDG Budapest","id":6397942,"join_mode":"open","lat":47.5099983215332,"lon":19.079999923706055,"urlname":"GDG-Budapest","who":"GDG Budapester","localized_location":"Budapest, Hungary","state":"","country":"hu","region":"en_US","timezone":"Europe/Budapest"},"link":"https://www.meetup.com/GDG-Budapest/events/145854122/","description":"<p>Second GDG Budapest meetup! <br/>Each presentation takes 15-30 minutes.</p> <p>Language of the meeting: Hungarian + English.</p> <p>Please register on this page and follow us on Google Plus: <a href=\"https://plus.google.com/109554147114014091559/posts\"><a href=\"https://plus.google.com/109554147114014091559/posts\" class=\"linkified\">https://plus.google.com/109554147114014091559/posts</a></a> </p> <p>Topics: <br/>1.) GWT (Google Web Toolkit) - What is GWT, Mini-Project<br/>Harangozó Gábor</p> <p>2.) Google Apps Script  - Google's Cloud (server side) scripting language based on Javascript 1.8.<br/>Amr Mohamed Abdelwahab (<a href=\"https://plus.google.com/104462989108970605029/\" class=\"linkified\">https://plus.google.com/104462989108970605029/</a>)</p> ","how_to_find_us":"Between Lehel square and Dózsa Gy. Street.","visibility":"public"},{"created":1385489974000,"id":"152827052","name":"GDG Budapest December","rsvp_limit":40,"date_in_series_pattern":false,"status":"past","time":1386612000000,"local_date":"2013-12-09","local_time":"19:00","updated":1386660560000,"utc_offset":3600000,"waitlist_count":0,"yes_rsvp_count":13,"venue":{"id":15347352,"name":"Cloudoffice 1","lat":47.52043914794922,"lon":19.06551170349121,"repinned":false,"address_1":"Váci út 19, 1st floor (entrance form Lőportár St.)","address_2":"Panoráma Irodaház","city":"Budapest","country":"hu","localized_country_name":"Hungary"},"group":{"created":1356866254000,"name":"GDG Budapest","id":6397942,"join_mode":"open","lat":47.5099983215332,"lon":19.079999923706055,"urlname":"GDG-Budapest","who":"GDG Budapester","localized_location":"Budapest, Hungary","state":"","country":"hu","region":"en_US","timezone":"Europe/Budapest"},"link":"https://www.meetup.com/GDG-Budapest/events/152827052/","description":"<p>GDG Budapest utolsó meetup 2013-ban.</p> <p>Két témánk lesz:</p> <p><b>Etical Hack</b> - <a href=\"https://plus.google.com/107759858376123872275/posts\">Kollár György</a></p> <p>Live demo - SQL (és nem php) injection</p> <p><b>Kinek a felelőssége? -Fejlesztő, Rendszergazda,Üzemeltető?</b></p> <p>Egy kevés jog az emelt szintű szakmai felelősségről, tájékoztatási kötelezettségről - Kóczán Béla</p> <p>A végén <b>beszélgetés és Pizza és Sör</b> :-)</p> ","how_to_find_us":"Váci út 19, 1st floor (entrance form Lőportár St.)","visibility":"public"},{"created":1390258220000,"id":"161627502","name":"GDG Budapest Január","rsvp_limit":40,"date_in_series_pattern":false,"status":"past","time":1390845600000,"local_date":"2014-01-27","local_time":"19:00","updated":1390895794000,"utc_offset":3600000,"waitlist_count":0,"yes_rsvp_count":8,"venue":{"id":15347352,"name":"Cloudoffice 1","lat":47.52043914794922,"lon":19.06551170349121,"repinned":false,"address_1":"Váci út 19, 1st floor (entrance form Lőportár St.)","address_2":"Panoráma Irodaház","city":"Budapest","country":"hu","localized_country_name":"Hungary"},"group":{"created":1356866254000,"name":"GDG Budapest","id":6397942,"join_mode":"open","lat":47.5099983215332,"lon":19.079999923706055,"urlname":"GDG-Budapest","who":"GDG Budapester","localized_location":"Budapest, Hungary","state":"","country":"hu","region":"en_US","timezone":"Europe/Budapest"},"link":"https://www.meetup.com/GDG-Budapest/events/161627502/","manual_attendance_count":11,"description":"<p>2014 Első meetupja.</p> <p>Egy témánk biztosan lesz, de igyekszem még egy előadót beszervezni.</p> <p>Németh Attila (<a href=\"https://plus.google.com/106511257695325614284\"><a href=\"https://plus.google.com/106511257695325614284\" class=\"linkified\">https://plus.google.com/106511257695325614284</a></a>): </p> <p>Analytics Adatok lekérése és publikálása Google Chart és Core Reporting API segítségével.</p> <p>A nap végén beszélgetés és sör, pizza, üditő.</p> <p>A belépés ingyenes, várok mindenkit szeretettel.</p> ","how_to_find_us":"Dózsa György út és a Lehel tér között van, a Lőportar utca felöl van a bejárat.","visibility":"public"},{"created":1392211854000,"id":"165918902","name":"Google Developer Group Budapest - February","rsvp_limit":40,"date_in_series_pattern":false,"status":"past","time":1393264800000,"local_date":"2014-02-24","local_time":"19:00","updated":1393276059000,"utc_offset":3600000,"waitlist_count":0,"yes_rsvp_count":4,"venue":{"id":15347352,"name":"Cloudoffice 1","lat":47.52043914794922,"lon":19.06551170349121,"repinned":false,"address_1":"Váci út 19, 1st floor (entrance form Lőportár St.)","address_2":"Panoráma Irodaház","city":"Budapest","country":"hu","localized_country_name":"Hungary"},"group":{"created":1356866254000,"name":"GDG Budapest","id":6397942,"join_mode":"open","lat":47.5099983215332,"lon":19.079999923706055,"urlname":"GDG-Budapest","who":"GDG Budapester","localized_location":"Budapest, Hungary","state":"","country":"hu","region":"en_US","timezone":"Europe/Budapest"},"link":"https://www.meetup.com/GDG-Budapest/events/165918902/","description":"<p>Adwords API with Python (on App Engine).</p> <p>Amr Mohamed Abdelwahab (<a href=\"https://plus.google.com/104462989108970605029/\"><a href=\"https://plus.google.com/104462989108970605029/\" class=\"linkified\">https://plus.google.com/104462989108970605029/</a></a>) </p> ","visibility":"public"},{"created":1396625520000,"id":"175332492","name":"GDG Budapest April - Unity 3D","date_in_series_pattern":false,"status":"past","time":1397494800000,"local_date":"2014-04-14","local_time":"19:00","updated":1397562568000,"utc_offset":7200000,"waitlist_count":0,"yes_rsvp_count":6,"venue":{"id":17550262,"name":"Kálvin tér - California Coffee Company","lat":47.489959716796875,"lon":19.062240600585938,"repinned":false,"address_1":"Kálvin tér 12.","city":"Budapest","country":"hu","localized_country_name":"Hungary"},"group":{"created":1356866254000,"name":"GDG Budapest","id":6397942,"join_mode":"open","lat":47.5099983215332,"lon":19.079999923706055,"urlname":"GDG-Budapest","who":"GDG Budapester","localized_location":"Budapest, Hungary","state":"","country":"hu","region":"en_US","timezone":"Europe/Budapest"},"link":"https://www.meetup.com/GDG-Budapest/events/175332492/","description":"<p>Közös Meetup a Unity 3D Csoporttal. </p> <p>\"Talk, share, have fun\"</p> <p>Kérem, hogy aki jön az a Google oldalakon is jelezze. Köszönöm.<br/><a href=\"http://goo.gl/SDb3k6\"><a href=\"http://goo.gl/SDb3k6\" class=\"linkified\">http://goo.gl/SDb3k6</a></a></p> ","visibility":"public"},{"created":1402932456000,"duration":115140000,"id":"189364432","name":"Google I/O Extended Budapest - 2 nap a BME-n!","date_in_series_pattern":false,"status":"past","time":1403704800000,"local_date":"2014-06-25","local_time":"16:00","updated":1403851371000,"utc_offset":7200000,"waitlist_count":0,"yes_rsvp_count":17,"venue":{"id":20728832,"name":"BME Q épület","lat":47.47251892089844,"lon":19.059730529785156,"repinned":false,"address_1":"Magyar Tudósok körútja 2. ","city":"Budapest","country":"hu","localized_country_name":"Hungary"},"group":{"created":1356866254000,"name":"GDG Budapest","id":6397942,"join_mode":"open","lat":47.5099983215332,"lon":19.079999923706055,"urlname":"GDG-Budapest","who":"GDG Budapester","localized_location":"Budapest, Hungary","state":"","country":"hu","region":"en_US","timezone":"Europe/Budapest"},"link":"https://www.meetup.com/GDG-Budapest/events/189364432/","description":"<p>A  BME Automatizálási és Alkalmazott Informatikai Tanszék idén is megrendezi a Google I/O Extended eseményt. A GDG Budapest ehhez a rendzevényhez csatlakozik.</p> <p>Kérem, hogy az ő oldalukon is jelezzétek a részvételi szándékot: </p> <p><a href=\"http://goo.gl/hAozjk\"><a href=\"http://goo.gl/hAozjk\" class=\"linkified\">http://goo.gl/hAozjk</a></a></p> <p>﻿Eddigi Programok (a további részletekért a google plus-os oldalt nézzétek)?</p> <p>Eddig előadások és előadók (a lista folyamatosan bővül):<br/>- Cast-old magad TV-re (Gerencsér Péter)<br/>- Felhasználói felület tervezés és design mobil környezetben (Dér Kristóf)<br/>- Android alkalmazások fejlesztése webes technológiákkal (Fehér Marcell)<br/>- Függőség kezelési eszközök és lehetőségek Android platformon (Erdődy-Nagy Zsombor)<br/>- Modern szoftverfejlesztési módszerek alkalmazása Android környezetben (Ekler Péter)<br/>- Cloud és BigData megoldások Google platformon</p> <p>További néhány téma a tervezett élő előadásokból:<br/>- Android fejlesztés (újdonságok, best practicek, külső osztálykönyvtárak)<br/>- Agilis mobil szoftverfejlesztés módszerei és eszközei<br/>- Cross platform szoftverfejlesztés<br/>- Játékfejlesztés Android platformon<br/>- Felhő szolgáltatások<br/>- Android beágyazott környezetben<br/>- Demok és sikertörténetek helyi kötődésű cégektől<br/>- Közös hands-on fejlesztés</p> <p>Az eseményt a BME VIK AUT-on ők szervezik:<br/>Charaf Hassan, Ekler Péter, Forstner Bertalan</p> <p>Pizzát és Sört a <a href=\"http://yappp.com/\">YAPPP</a> biztosÍtja</p> ","visibility":"public"},{"created":1410948204000,"id":"207769542","name":"GDG - Budapest - Szeptember","rsvp_limit":15,"date_in_series_pattern":false,"status":"past","time":1411750800000,"local_date":"2014-09-26","local_time":"19:00","updated":1411763215000,"utc_offset":7200000,"waitlist_count":0,"yes_rsvp_count":4,"venue":{"id":17550262,"name":"Kálvin tér - California Coffee Company","lat":47.489959716796875,"lon":19.062240600585938,"repinned":false,"address_1":"Kálvin tér 12.","city":"Budapest","country":"hu","localized_country_name":"Hungary"},"group":{"created":1356866254000,"name":"GDG Budapest","id":6397942,"join_mode":"open","lat":47.5099983215332,"lon":19.079999923706055,"urlname":"GDG-Budapest","who":"GDG Budapester","localized_location":"Budapest, Hungary","state":"","country":"hu","region":"en_US","timezone":"Europe/Budapest"},"link":"https://www.meetup.com/GDG-Budapest/events/207769542/","description":"<p>Kötetlen beszélgetés - Networking. Szívesen látnék App Engine fejlesztőket, és Apps Script fejlesztőket is.</p> <p>Több mint 15 résztvevő esetén változhat a helyszin.</p> ","how_to_find_us":"A Nmezeti Múzeum felöl van a bejárat","visibility":"public"},{"created":1418782679000,"id":"219287517","name":"GDG Budapest - December","date_in_series_pattern":false,"status":"past","time":1418839200000,"local_date":"2014-12-17","local_time":"19:00","updated":1418850819000,"utc_offset":3600000,"waitlist_count":0,"yes_rsvp_count":4,"venue":{"id":22239682,"name":"Ankert","lat":47.50136184692383,"lon":19.05915069580078,"repinned":false,"address_1":"1061, Paulay Ede u. 33., Budapest","city":"Budapest","country":"hu","localized_country_name":"Hungary"},"group":{"created":1356866254000,"name":"GDG Budapest","id":6397942,"join_mode":"open","lat":47.5099983215332,"lon":19.079999923706055,"urlname":"GDG-Budapest","who":"GDG Budapester","localized_location":"Budapest, Hungary","state":"","country":"hu","region":"en_US","timezone":"Europe/Budapest"},"link":"https://www.meetup.com/GDG-Budapest/events/219287517/","description":"<p>Kötetlen beszélgetés - Networking. Szívesen látnék App Engine fejlesztőket, és Apps Script fejlesztőket is.</p> <p><a href=\"https://developers.google.com/events/5771282011389952/\"><a href=\"https://developers.google.com/events/5771282011389952/\" class=\"linkified\">https://developers.google.com/events/5771282011389952/</a></a></p> <p>Decemberben az összes tech meetupot és meetuppert szeretnék egy nagy közös találkozóra összerántani. Erre az alkalomra nem szervezünk előadásokat, hanem csak szabadon beszélgetni és iszogatni jönnénk össze, akár halkan még szakmázni is ér. Évad zárós, éves bölcsességeket levonós, elő-karácsonyozós, sörözős-fröccsözős, és legfőképpen vegyes meetupos esemény lesz, gyertek!</p> <p>A helyszín az Ankert lesz, ahol a hátsó rész csak a miénk, és a konyha is üzemelni fog. Ha pedig belehúznál a hideg elleni küzdelembe a pultnál, kapunk 10% kedvezményt a Kozel sörre és a Bols vodkára.</p> <p>További információk az esemény Facebook oldalán:</p> <p><a href=\"https://www.facebook.com/events/971102629583977\"><a href=\"https://www.facebook.com/events/971102629583977\" class=\"linkified\">https://www.facebook.com/events/971102629583977</a></a> </p> <p>[English] In December we would like to invite all the meetups and metuppers for a big bash together. For this event we are not preparing any talks, we would just gather for some chat and drinks, maybe some professional jibber-jabber quitely, too. Year-ending with the annual wise thoughts, pre-Xmas, beers &amp; spritzer, and most importantly cross-meetup - don’t miss it! Venue is going to be Ankert where all the back area will be provided for us. The kitchen will be operating, and if you happen to feel cold you can get 10% off of Kozel beers and Bols vodka. </p> ","visibility":"public"},{"created":1423671482000,"duration":10800000,"id":"220457681","name":"Android Studio Plugin fejlesztés, Gradle, IntelliJ, Dynamic Resource Management","rsvp_limit":70,"date_in_series_pattern":false,"status":"past","time":1424419200000,"local_date":"2015-02-20","local_time":"09:00","updated":1424720003000,"utc_offset":3600000,"waitlist_count":0,"yes_rsvp_count":23,"venue":{"id":19632702,"name":"Google Grund","lat":47.484920501708984,"lon":19.075969696044922,"repinned":false,"address_1":"1082 Budapest, Nagytemplom utca 30.","city":"Budapest","country":"hu","localized_country_name":"Hungary"},"group":{"created":1356866254000,"name":"GDG Budapest","id":6397942,"join_mode":"open","lat":47.5099983215332,"lon":19.079999923706055,"urlname":"GDG-Budapest","who":"GDG Budapester","localized_location":"Budapest, Hungary","state":"","country":"hu","region":"en_US","timezone":"Europe/Budapest"},"link":"https://www.meetup.com/GDG-Budapest/events/220457681/","description":"<p>Újra GDG Budapest Rendezvény!</p> <p>Az előadások:</p> <p><b>Android studio új lehetőségek, esettanulmányok</b></p> <p>· Történeti áttekintés – múlt és jövő. Előadó: Dr. Ekler Péter – BME AUT</p> <p>· AS újdonságai. Dr. Ekler Péter - BME AUT</p> <p>· AS valódi előnyök. Gerencsér Péter - BME AUT</p> <p>o <b>IntelliJ mint platform</b>. Szeibert Ádám - ITware</p> <p>o <b>Gradle mint build tool </b>(manifest merger, product flavors, build types). Szeibert Ádám - ITware</p> <p>· <b>Migrálás AS-re </b>(Nativer). Előadó: Donigold Péter - Transround</p> <p>o <b>Plugin development </b>(disztributálható fejlesztői környezet kialakítása). Szeibert Ádám - ITware</p> <p>o</p> <p><b>Workshop: multilingual runtime extension beépítése</b></p> <p>. Szeibert Ádám - ITware</p> <p>Várunk Mindenkit szeretettel.</p> <p>A Helyszint a Google, a kaját meg a Transround Biztosítja.</p> ","how_to_find_us":"Keresztül a játszótéren, be a kocsmába, majd balra hátul ki, ott már látjátok...","visibility":"public"},{"created":1431535079000,"id":"222507133","name":"Google I/O elötti kötetlen beszélgetés","date_in_series_pattern":false,"status":"past","time":1432054800000,"local_date":"2015-05-19","local_time":"19:00","updated":1432067907000,"utc_offset":7200000,"waitlist_count":0,"yes_rsvp_count":1,"venue":{"id":17550262,"name":"Kálvin tér - California Coffee Company","lat":47.489959716796875,"lon":19.062240600585938,"repinned":false,"address_1":"Kálvin tér 12.","city":"Budapest","country":"hu","localized_country_name":"Hungary"},"group":{"created":1356866254000,"name":"GDG Budapest","id":6397942,"join_mode":"open","lat":47.5099983215332,"lon":19.079999923706055,"urlname":"GDG-Budapest","who":"GDG Budapester","localized_location":"Budapest, Hungary","state":"","country":"hu","region":"en_US","timezone":"Europe/Budapest"},"link":"https://www.meetup.com/GDG-Budapest/events/222507133/","how_to_find_us":"A helyszín még változhat, ellenőrizzétek mielött jöttök.","visibility":"public"},{"created":1431535781000,"duration":104400000,"id":"222507350","name":"Google I/O Extended 2015 Budapest","date_in_series_pattern":false,"status":"past","time":1432825200000,"local_date":"2015-05-28","local_time":"17:00","updated":1432931161000,"utc_offset":7200000,"waitlist_count":0,"yes_rsvp_count":20,"venue":{"id":20728832,"name":"BME Q épület","lat":47.47251892089844,"lon":19.059730529785156,"repinned":false,"address_1":"Magyar Tudósok körútja 2. ","city":"Budapest","country":"hu","localized_country_name":"Hungary"},"group":{"created":1356866254000,"name":"GDG Budapest","id":6397942,"join_mode":"open","lat":47.5099983215332,"lon":19.079999923706055,"urlname":"GDG-Budapest","who":"GDG Budapester","localized_location":"Budapest, Hungary","state":"","country":"hu","region":"en_US","timezone":"Europe/Budapest"},"link":"https://www.meetup.com/GDG-Budapest/events/222507350/","description":"<p>Google I/O Extended Event Budapest - 2015 - <a href=\"https://plus.google.com/events/ch6q32khg2lk8cjviv4rcr838j4\"><a href=\"https://plus.google.com/events/ch6q32khg2lk8cjviv4rcr838j4\" class=\"linkified\">https://plus.google.com/events/ch6q32khg2lk8cjviv4rcr838j4</a></a><br/>BME VIK AUT</p> <p>A Budapesti Műszaki és Gazdaságtudományi Egyetem Villamosmérnöki és Informatika Karán, az Automatizálási és Alkalmazott Informatikai Tanszék idén is (immár harmadik alkalommal) megrendezi a Google I/O Extended eseményt.<br/>A rendezvény egy kiváló alkalom, mindazoknak akik első kézből szeretnének hallani a Google technológiai újdonságairól, de személyesen nem tudnak részt venni a San Francisco-i eseményen.</p> <p>Az esemény helyszíne a BME Q épülete: Budapest, Magyar tudósok körútja 2.<br/>Várható kezdés május 28-án 17 órától, május 29-én 16 órától!</p> <p>Program: hamarosan...</p> <p>A rendezvényen élőben sugározzuk a legfontosabb előadásokat, valamint rengeteg érdekes és izgalmas téma kerül bemutatásra hazai fejlesztőktől és szakértőktől.</p> <p>Az esemény szervezője: BME VIK AUT<br/>Charaf Hassan, Ekler Péter, Forstner Bertalan, Imre Kelényi</p> <p>Tervezett előadások (a lista folyamatosan bővül):<br/>- Újdonságok az ASUS műhelyéből (ASUS)<br/>- ROBserver, robotizált megfigyelési szolgáltatások fejlesztésére (RoBserver)<br/>- Közösségi hálózatok integrálása Android platformon (Inotay Krisztián)<br/>- Az Angular 2.0 újdonságai (Tomka Anna/Hernesz Gergő/Szabó Ádám)<br/>- Memória adatbázisok fejlesztői szemszögből, Redis Cluster (Hernesz Gergő)<br/>- Tesztelési eszközök és lehetőségek Andoid patformon (Mostoha Roland)<br/>- Test Driven Development Android környezetben (Ekler Péter)<br/>- Külső osztálykönyvtárak, mint fejlesztő eszközök Android platformon (Balogh Tamás)<br/>- Kódgenerálás Android környezetben (Balogh Tamás)<br/>- Redis és Redis cluster a gyarkolatban (Hernesz Gergely)<br/>- Az Angular 2.0 újdonságai (Tomka Anna)<br/>- Tesztelési eszközök és lehetőségek reszponzív webes frontend megoldások fejlesztése során (Szabó Ádám)<br/>- Esettanulmány: Fizikai kísérletek támogatása mobil készülékekkel<br/>- Android Studio újdonságok és eszközök (Gerencsér Péter)</p> <p>In English:</p> <p>We are pleased to announce that we are organizing an extended Google I/O event at Budapest University of Technology, Department of Automation and Applied informatics. If you can't attend on the San Francisco Google I/O event in person, this is a good opportunity to watch the keynote events together and participate on interesting events related to Google technologies.</p> <p>The event will be located at the building Q of Budapest University of Technology and Economics: Budapest, Magyar tudósok körútja 2.</p> <p>During the event of course we broadcast the Google I/O keynote events and other selected presentations.</p> <p>Besides there will be several presenters from the university and the industry as well in the following topics:<br/>- TBD</p> <p>The host of the events is: BME VIK AUT<br/>Hassan Charaf, Péter Ekler, Bertalan Forstner, Imre Kelényi﻿</p> ","how_to_find_us":"https://plus.google.com/events/ch6q32khg2lk8cjviv4rcr838j4","visibility":"public"},{"created":1433432480000,"duration":25200000,"id":"223015209","name":"Android TV Codelab - workshop","rsvp_limit":80,"date_in_series_pattern":false,"status":"past","time":1434697200000,"local_date":"2015-06-19","local_time":"09:00","updated":1434814814000,"utc_offset":7200000,"waitlist_count":0,"yes_rsvp_count":23,"venue":{"id":19632702,"name":"Google Grund","lat":47.484920501708984,"lon":19.075969696044922,"repinned":false,"address_1":"1082 Budapest, Nagytemplom utca 30.","city":"Budapest","country":"hu","localized_country_name":"Hungary"},"group":{"created":1356866254000,"name":"GDG Budapest","id":6397942,"join_mode":"open","lat":47.5099983215332,"lon":19.079999923706055,"urlname":"GDG-Budapest","who":"GDG Budapester","localized_location":"Budapest, Hungary","state":"","country":"hu","region":"en_US","timezone":"Europe/Budapest"},"link":"https://www.meetup.com/GDG-Budapest/events/223015209/","description":"<p><b>Fejlesztés Android TV platformra - Codelab - Az előadások angolul lesznek!<br/>Előadó: Piotr Herod, TP Vision Europe B.V.</b></p> <p>Az előadást két egységre bontjuk:</p> <p>· egy <b>szemináriumral</b>, ahol az Android TV platformra történő fejlesztés specifikációiról hallhatnak</p> <p>· egy <b>workshopra</b>, ahol a rendelkezésre álló eszközök segítségével maguk is tesztelhetik a platform működését.</p> <p><b>How to prepare for the codelab?</b></p> <p>- Bring your own laptop, with the operating system you know</p> <p>- Don't forget a charger :)</p> <p>- Have the latest version of Android Studio installed [masked])</p> <p>- Android 5.0.1 (API 21) SDK installed and updated</p> <p>- [optionally] Android 5.1 (API 22) SDK installed and updated</p> <p>- Android TV Intel x86 Atom System Image installed</p> <p>- Android SDK Tootls / Platform-tools and Build-tools installed</p> <p>- Android support library installed</p> <p>- Git installed</p> <p>Be prepared to work on both emulator and real Android TV devices. Availability of Android TV devices depends on attendance</p> <p><b>09:00 - 09:30</b></p> <p>Welcome</p> <p><b>09:30 - 10:30</b></p> <p>Android on a big screen; Philips TV Powered by Android™ lineup in 2015</p> <p><b>10:30 - 11:00</b></p> <p>Guest Speaker – Hungarian App developer</p> <p><b>11:00 - 12:30</b></p> <p>Android TV Leanback Library <a href=\"http://androidtv-codelabs.appspot.com/static/codelabs/1-androidtv-adding-leanback/#1\">codelab</a></p> <p><b>12:30 - 13:30</b></p> <p>Lunch</p> <p><b>13:30 - 16:00</b></p> <p>Android TV Leanback Library codelab continued</p> <p>Várunk mindenkit szeretettel.</p> ","visibility":"public"},{"created":1450364561000,"id":"227477250","name":"GDG Budapest - Évzáró","date_in_series_pattern":false,"status":"past","time":1450720800000,"local_date":"2015-12-21","local_time":"19:00","updated":1450733052000,"utc_offset":3600000,"waitlist_count":0,"yes_rsvp_count":1,"venue":{"id":17550262,"name":"Kálvin tér - California Coffee Company","lat":47.489959716796875,"lon":19.062240600585938,"repinned":false,"address_1":"Kálvin tér 12.","city":"Budapest","country":"hu","localized_country_name":"Hungary"},"group":{"created":1356866254000,"name":"GDG Budapest","id":6397942,"join_mode":"open","lat":47.5099983215332,"lon":19.079999923706055,"urlname":"GDG-Budapest","who":"GDG Budapester","localized_location":"Budapest, Hungary","state":"","country":"hu","region":"en_US","timezone":"Europe/Budapest"},"link":"https://www.meetup.com/GDG-Budapest/events/227477250/","description":"<p>Évzáró beszélgetés</p> <p>Hogyan tovább?</p> ","visibility":"public"},{"created":1462389434000,"duration":195300000,"id":"230877209","name":"Google I/O Extended - Budapest","date_in_series_pattern":false,"status":"past","time":1463579100000,"local_date":"2016-05-18","local_time":"15:45","updated":1463775117000,"utc_offset":7200000,"waitlist_count":0,"yes_rsvp_count":15,"venue":{"id":20728832,"name":"BME Q épület","lat":47.47251892089844,"lon":19.059730529785156,"repinned":false,"address_1":"Magyar Tudósok körútja 2. ","city":"Budapest","country":"hu","localized_country_name":"Hungary"},"group":{"created":1356866254000,"name":"GDG Budapest","id":6397942,"join_mode":"open","lat":47.5099983215332,"lon":19.079999923706055,"urlname":"GDG-Budapest","who":"GDG Budapester","localized_location":"Budapest, Hungary","state":"","country":"hu","region":"en_US","timezone":"Europe/Budapest"},"link":"https://www.meetup.com/GDG-Budapest/events/230877209/","description":"<p>Google I/O Extended Event Budapest - 2016</p> <p>BME VIK AUT</p> <p>A Budapesti Műszaki és Gazdaságtudományi Egyetem Villamosmérnöki és Informatika Karán, az Automatizálási és Alkalmazott Informatikai Tanszék idén is (immár negyedik alkalommal) megrendezi a Google I/O Extended eseményt.</p> <p>A rendezvény egy kiváló alkalom, mindazoknak akik első kézből szeretnének hallani a Google technológiai újdonságairól, de személyesen nem tudnak részt venni a San Francisco-i eseményen.</p> <p>Az esemény helyszíne a BME Q épülete: Budapest, Magyar tudósok körútja 2.</p> <p>Várható kezdés május 18-án 16 órától!</p> <p>A rendezvényen várhatóan élőben sugározzuk a legfontosabb előadásokat, valamint rengeteg érdekes és izgalmas téma kerül bemutatásra hazai fejlesztőktől és szakértőktől.</p> <p>Az esemény szervezője: BME VIK AUT</p> <p>Ekler Péter, Forstner Bertalan, Charaf Hassan</p> <p>Tervezett program (a változtatás jogát fenntartjuk):</p> <p>Terem: QBF 14-15</p> <p>Május 18-19:</p> <p>* Reaktív programozás Android platformon - Balogh Tamás</p> <p>* Irány a háttérbe! (Android architektúra) - Gerencsér Péter</p> <p>* Kotlin, Swift tapasztalatok</p> <p>* Teszteljünk Androidon! - Mostoha Roland</p> <p>* Android 6(7) és Android Studio újdonságok - Ekler Péter</p> <p>* BigData eszközök és legjobb gyakorlatok - Tömösvári Imre</p> <p>* Java 8 összefoglaló - Berkecz Ádám</p> <p>* Legújabb crossplatform megoldások (Ionic, stb.) - Tomka Anna</p> <p>* UX/UI - Dér Kristóf</p> <p>* Ügyfélélmény kontra bankbiztonság; lehetőségek és korlátok - Fekete György (Gránit Bank)</p> <p>English:</p> <p>We are pleased to announce that we are organizing an extended Google I/O event at Budapest University of Technology, Department of Automation and Applied informatics. If you can't attend on the San Francisco Google I/O event in person, this is a good opportunity to watch the keynote events together and participate on interesting events related to Google technologies.</p> <p>The event will be located at the building Q of Budapest University of Technology and Economics: Budapest, Magyar tudósok körútja 2.</p> <p>During the event of course we broadcast the Google I/O keynote events and other selected presentations.</p> <p>Besides there will be several presenters from the university and the industry as well.</p> <p>The host of the events is: BME VIK AUT</p> <p>Péter Ekler, Bertalan Forstner, Hassan Charaf﻿</p> ","visibility":"public"},{"created":1470590172000,"id":"233187657","name":"Ki szeretne, hajlandó oktatni? - Kötetlen beszélgetés néhány SÖR mellett.","rsvp_limit":8,"date_in_series_pattern":false,"status":"past","time":1471451400000,"local_date":"2016-08-17","local_time":"18:30","updated":1471464434000,"utc_offset":7200000,"waitlist_count":0,"yes_rsvp_count":4,"venue":{"id":24706531,"name":"Mókus Sörkert","lat":47.53739929199219,"lon":19.04390525817871,"repinned":false,"address_1":"Mókus u. 1-3, 1036","city":"Budapest","country":"hu","localized_country_name":"Hungary"},"group":{"created":1356866254000,"name":"GDG Budapest","id":6397942,"join_mode":"open","lat":47.5099983215332,"lon":19.079999923706055,"urlname":"GDG-Budapest","who":"GDG Budapester","localized_location":"Budapest, Hungary","state":"","country":"hu","region":"en_US","timezone":"Europe/Budapest"},"link":"https://www.meetup.com/GDG-Budapest/events/233187657/","description":"<p>Akik szeretnének Oktatni másokat, önkéntes és nonprofit alapon (persze azért elismertséget, tapasztalatot lehet vele szerezni, nem is keveset) azok (is) jöjjenek.</p> <p>És várom azokat is, akik csak meginnának egy jó sört, meg beszélgetnének.</p> ","how_to_find_us":"Árpád híd Budai hídfőnél van. Google Maps odavezet :-)","visibility":"public"},{"created":1471624219000,"duration":10800000,"id":"233472773","name":"Google Cloud Platform in a Practical way","rsvp_limit":40,"date_in_series_pattern":false,"status":"past","time":1472920200000,"local_date":"2016-09-03","local_time":"18:30","rsvp_close_offset":"PT5H30M","updated":1472985257000,"utc_offset":7200000,"waitlist_count":0,"yes_rsvp_count":34,"venue":{"id":24370606,"name":"Instant ","lat":47.50460433959961,"lon":19.058412551879883,"repinned":false,"address_1":"Budapest, Nagymező u. 38, 1065","city":"Budapest","country":"hu","localized_country_name":"Hungary"},"group":{"created":1356866254000,"name":"GDG Budapest","id":6397942,"join_mode":"open","lat":47.5099983215332,"lon":19.079999923706055,"urlname":"GDG-Budapest","who":"GDG Budapester","localized_location":"Budapest, Hungary","state":"","country":"hu","region":"en_US","timezone":"Europe/Budapest"},"link":"https://www.meetup.com/GDG-Budapest/events/233472773/","description":"<p><b>Google Cloud Platform in a Practical way</b></p> <p><a href=\"https://developers.google.com/experts/people/jerome-mouton\">Jerome Mouton</a> (co-founder and CTO at SnapEngage) will come to Budapest, and he offered to give a presentation. The presentation is about his personal experiences as developer (worth to see his linkedin profile: <a href=\"https://www.linkedin.com/in/jeromemouton\">linkedin.com/in/jeromemouton</a> ) on Google Cloud (Google AppEngine, Google CloudStorage, Google BigQuery, Google Compute Engine).</p> <p><b>UPDATE</b><br/>Judit Alföldi, who is a software developer at <a href=\"http://invenshure.com/hungary/\">Invensure Hungary</a> will talk about an online application that is used in the medical technology with the help of Google OAuth. Her presentation will be in Hungarian but the slides will be written in English.</p> <p>Sorry for the short notice and the unusual time (Saturday evening - however if you want to party, still have time after the meetup :-) )</p> <p>Places are limited, so say yes, if you really will come. Thanks.</p> ","how_to_find_us":"We will be in the gallery section of the venue which is at the far end of the venue, on the left.","visibility":"public"},{"created":1478616065000,"id":"235439215","name":" Közösségépítés, Szervezők, Témák - GDG jövője","date_in_series_pattern":false,"status":"past","time":1479835800000,"local_date":"2016-11-22","local_time":"18:30","updated":1479887194000,"utc_offset":3600000,"waitlist_count":0,"yes_rsvp_count":14,"venue":{"id":24370606,"name":"Instant ","lat":47.50460433959961,"lon":19.058412551879883,"repinned":false,"address_1":"Budapest, Nagymező u. 38, 1065","city":"Budapest","country":"hu","localized_country_name":"Hungary"},"group":{"created":1356866254000,"name":"GDG Budapest","id":6397942,"join_mode":"open","lat":47.5099983215332,"lon":19.079999923706055,"urlname":"GDG-Budapest","who":"GDG Budapester","localized_location":"Budapest, Hungary","state":"","country":"hu","region":"en_US","timezone":"Europe/Budapest"},"link":"https://www.meetup.com/GDG-Budapest/events/235439215/","description":"<p>Sziasztok,</p> <p>Szólj bele a GDG jövőjébe.<br/>Csatlakozzatok hozzánk egy beszélgetésre, ahol megismerkedhetünk egymással, illetve megoszthatjátok témaötleteiteket a következő meetupokra - kíváncsiak vagyunk, hogy TI miről hallanátok szívesen.</p> <p>Miért jó szervezőnek lenni. Pár szó a GDG szervezésről.</p> <p>Sneak peak: december 7-én az Androidé a főszerep - erről bővebben hamarosan.</p> <p>Továbbá szívesen várjuk szervezői ambícióval rendelkező tagok jelentkezését is.</p> <p>Találkozzunk tehát november 22-én az Instant hátsó termében!</p> ","how_to_find_us":"A \"galéria\" részen leszünk, mely a pultok mögött található a földszinten.","visibility":"public"},{"created":1479934774000,"id":"235786581","name":"Deep Dive into Angular 2","rsvp_limit":2,"date_in_series_pattern":false,"status":"past","time":1480701600000,"local_date":"2016-12-02","local_time":"19:00","updated":1480713304000,"utc_offset":3600000,"waitlist_count":0,"yes_rsvp_count":2,"group":{"created":1356866254000,"name":"GDG Budapest","id":6397942,"join_mode":"open","lat":47.5099983215332,"lon":19.079999923706055,"urlname":"GDG-Budapest","who":"GDG Budapester","localized_location":"Budapest, Hungary","state":"","country":"hu","region":"en_US","timezone":"Europe/Budapest"},"link":"https://www.meetup.com/GDG-Budapest/events/235786581/","description":"<p><b>Please RSVP at the <a href=\"https://www.meetup.com/AngularBP/events/234144845/\">Angular Meetup event</a>.</p> <p>On the 2nd of December, we'll have a great event, which we organize together with the <a href=\"https://www.meetup.com/AngularBP/\">Angular Meetup Budapest</a>. The Venue will be the so called Google Grund, and we'll have an international guest speaker from Norway. </b></p> <p>On the 14th of September Angular 2 became production ready. There is no more reason to wait, it's high time to learn and jump deep into Angular 2. </p> <p>We already have an amazing guest speaker for this event. Maxim Salnikov #GDE is coming right from Oslo to support us on our journey in mastering Angular 2. </p> <p><img src=\"https://a248.e.akamai.net/secure.meetupstatic.com/photos/event/2/4/7/5/600_454149333.jpeg\" /></p> <p><b>Maxim Salnikov</b>, google developer expert in AngularJS &amp; Angular 2</p> <p><a href=\"https://developers.google.com/experts/people/maxim-salnikov\"><a href=\"https://developers.google.com/experts/people/maxim-salnikov\" class=\"linkified\">https://developers.google.com/experts/people/maxim-salnikov</a></a> </p> <p>Maxim Salnikov (aka webmaxru on Twitter/Github) is a Oslo-based web UI developer and a Google Developer Expert with strong passion to mobile. He has 10+ years experience in development front-ends for complex web applications. </p> <p>On evenings he runs Norway’s largest meetups dedicated to web front-end: Framsia, AngularJS Oslo. Also he is leader of Norway's biggest community dedicated to mobile development (Mobile Meetup Oslo) and currently working on organizing conference for mobile developers in 2016. </p> <p><b>Gabor Szmetanko &amp; Sandor Vasi: Angular E2E testing made easy </b><br/>------------------------------------------- <br/>End-to-end testing is a testing methodology for software applications that ensures accurate functioning of the application by testing it at all the layers right from the front-end to the back-end.</p> <p>In our talk we will introduce you to the world of Angular end-to-end testing. First, we will guide you through the basic concepts of Protractor and show you some simple end-to-end tests.</p> <p>Unfortunately, testing of real world apps isn't as easy as some tutorials and examples might suggest. We will highlight some pitfalls and show you best practices to avoid them.</p> <p>Finally, we will ng-show you a new tool that will let you focus on testing the actual business logic instead of hacking Protractor.</p> <p><b>Bio of the speakers</b></p> <p>Gabor Szmetanko and Sandor Vasi are fullstack web developers who have been programming &amp; building websites for over 10 years. They are enthusiastic about the Angular ecosystem and have been working with Angular based production applications since the very early years of Angular. They are founders of a small Hungarian development shop with large international clients in the aviaton and security sectors. They are actively involved in several open-source projects and are passionate about simplifying development processes.</p> <p><b>Venue:</b> <b>Because of the high volume of interested people we will move to a bigger venue - please follow the news at the <a href=\"https://www.meetup.com/AngularBP/events/234144845/\">Angular Meetup event</a>.</b></p> <p>The event is sponsored by <a href=\"http://www.reklammuvek.com/\">Reklámművek</a>.</p> <p><b>Please RSVP at the <a href=\"https://www.meetup.com/AngularBP/events/234144845/\">Angular Meetup event</a>.</b></p> ","visibility":"public"},{"created":1478775955000,"id":"235483821","name":"Android - hatékonyan (sorozat), 1. alkalom","date_in_series_pattern":false,"status":"past","time":1481128200000,"local_date":"2016-12-07","local_time":"17:30","updated":1482308073000,"utc_offset":3600000,"waitlist_count":0,"yes_rsvp_count":109,"venue":{"id":20728832,"name":"BME Q épület","lat":47.47251892089844,"lon":19.059730529785156,"repinned":false,"address_1":"Magyar Tudósok körútja 2. ","city":"Budapest","country":"hu","localized_country_name":"Hungary"},"group":{"created":1356866254000,"name":"GDG Budapest","id":6397942,"join_mode":"open","lat":47.5099983215332,"lon":19.079999923706055,"urlname":"GDG-Budapest","who":"GDG Budapester","localized_location":"Budapest, Hungary","state":"","country":"hu","region":"en_US","timezone":"Europe/Budapest"},"link":"https://www.meetup.com/GDG-Budapest/events/235483821/","description":"<p>17:30-17:50<br/>Gerencsér Péter: Android design patternek</p> <p>18:00-18:20<br/>Balogh Tamás: Android Architektúrák</p> <p>18:30-18:50<br/>Gerlei Balázs: Szabad-e? - Hogyan kérjünk futásidőben engedélyeket Androidon</p> <p>19:00-19:20<br/>Ekler Péter: Android API érdekességek - amiről kevés szó esik</p> ","how_to_find_us":"BME Q épület, QBF14-15ös terem","visibility":"public"},{"created":1481733456000,"id":"236238030","name":"Angular és környéke","rsvp_limit":80,"date_in_series_pattern":false,"status":"past","time":1487869200000,"local_date":"2017-02-23","local_time":"18:00","updated":1492000767000,"utc_offset":3600000,"waitlist_count":0,"yes_rsvp_count":80,"venue":{"id":23820270,"name":"Supercharge HQ","lat":47.49665069580078,"lon":19.057809829711914,"repinned":false,"address_1":"1075, Károly krt 9.","city":"Budapest","country":"hu","localized_country_name":"Hungary"},"group":{"created":1356866254000,"name":"GDG Budapest","id":6397942,"join_mode":"open","lat":47.5099983215332,"lon":19.079999923706055,"urlname":"GDG-Budapest","who":"GDG Budapester","localized_location":"Budapest, Hungary","state":"","country":"hu","region":"en_US","timezone":"Europe/Budapest"},"link":"https://www.meetup.com/GDG-Budapest/events/236238030/","description":"<p><b>Google Developer Group - Február - Angular</b></p> <p><b>Angular 2.0. vs. React<br/>Sipos Gergely, szoftverfejlesztő -  <a href=\"https://hu.linkedin.com/in/gergelysipos\"><a href=\"https://hu.linkedin.com/in/gergelysipos\" class=\"linkified\">https://hu.linkedin.com/in/gergelysipos</a></a><br/></b></p> <p>Az Angular 2.0 teljesen megújult az első verzióhoz képest, rengeteg problémát orvosolva, ám érdemes összehasonlítani a Reacttal, és megvizsgálni, hogy az ottani best practice-ek mennyire lehetnek hasznosak az Angular esetében. Az Angular mellé olyan a Reacthoz kapcsolódó frameworkok is hasznos kiegészítők lehetnek, mint például JSX, Reduxk.</p> <p><b>Angular CLI - Angular Best Practises<br/>Nagy Gergő <br/></b><br/>Angular projekt indítás az Angular CLI eszközzel, mappaszerkezet és eszközök használata. Bemutatjtuk, hogy hogy épül fel egy angular applikáció az angular-os csapat ajánlása szerint és hogyan érdemes rendezni a kódot. Illetve bemutatjuk, hogy milyen eszközöket biztosít számunkra az Angular CLI és mi mire jó, illetve gyors példákat is mutatunk.</p> <p><b>Angular Performance Optimalization</b><br/><b>Harangozó Gábor</b></p> <p>Az Angular teljesítménye nagyon jó, de egy nagyobb alkalmazásban szükség lehet extra teljesítmény kinyerésére is. Az előadás során szeretnénk pár technikát bemutatni amivel már az alkalmazás kezdeti lépésétől támogathatjuk az alkalmazásunk további teljesítmény növekedését(Lazy load, Change detection, Stream, AOT). Ezen mintákat az Angular CLI project-en mutatjuk be.</p> <p><b>Angular + Redux Összefoglaló<br/>Oláh Attila, Javascript Lead -  <a href=\"https://www.linkedin.com/in/attila-olah-6039b277/\"><a href=\"https://www.linkedin.com/in/attila-olah-6039b277/\" class=\"linkified\">https://www.linkedin.com/in/attila-olah-6039b277/</a></a></b></p> <p>Hogyan hozzuk ossze az Angulart (2+) es a React vilagabol ismert Redux-ot? Milyen problemara ad megoldast a Redux?Rovid Redux attekintes utan egy esettanulmanyon keresztul megnezzuk, hogyan mukodik az angular-redux (<a href=\"https://github.com/angular-redux\"><a href=\"https://github.com/angular-redux\" class=\"linkified\">https://github.com/angular-redux</a></a>) elesben.</p> <p>Várunk mindenkit!!</p> <p>A helyszínt és az ételt, italt a <a href=\"https://goo.gl/CM9PzW\">Supercharge</a> biztosítja<br/>A szervezést a <a href=\"https://goo.gl/x6zznM\">Doctusoft</a> és a <a href=\"https://goo.gl/to63Rd\">Reklámművek</a> adja</p> ","visibility":"public"},{"created":1485377495000,"id":"237198472","name":"Google Cloud Next '17 Extended - Budapest","date_in_series_pattern":false,"status":"past","time":1488990600000,"local_date":"2017-03-08","local_time":"17:30","updated":1489146102000,"utc_offset":3600000,"waitlist_count":0,"yes_rsvp_count":62,"venue":{"id":19632752,"name":"Google Ground","lat":47.484920501708984,"lon":19.075969696044922,"repinned":false,"address_1":"Nagytemplom utca 30.","city":"Budapest","country":"hu","localized_country_name":"Hungary"},"group":{"created":1356866254000,"name":"GDG Budapest","id":6397942,"join_mode":"open","lat":47.5099983215332,"lon":19.079999923706055,"urlname":"GDG-Budapest","who":"GDG Budapester","localized_location":"Budapest, Hungary","state":"","country":"hu","region":"en_US","timezone":"Europe/Budapest"},"link":"https://www.meetup.com/GDG-Budapest/events/237198472/","description":"<p>Attendee Survey:</p> <p><a href=\"https://goo.gl/r0MFKX\"><a href=\"https://goo.gl/r0MFKX\" class=\"linkified\">https://goo.gl/r0MFKX</a></a></p> <p>Please answer it!</p> <p>Google Cloud Next '17 Extended event in Budapest.</p> <p>During the event we stream the key sections and there will be also local presentations.</p> <p><b>Keynote Streaming (18:00 - )</b><br/>The keynote will feature the following speakers:</p> <p>• <a href=\"https://cloudnext.withgoogle.com/speakers#target=sundar-pichai[masked]-e6af-4fe6-8cf5-9bcc0286f250\">Sundar Pichai</a>, CEO, Google</p> <p>• <a href=\"https://cloudnext.withgoogle.com/speakers#target=diane-greene-c03bd4f3-c[masked]-b05b-756bddc22011\">Diane Greene</a>, Senior Vice President, Google Cloud</p> <p>• <a href=\"https://cloudnext.withgoogle.com/speakers#target=eric-schmidt-3f8c1e03-16b5-4adb-9684-b733a29bc6c2\">Eric Schmidt</a>, Executive Chairman, Alphabet, Inc.</p> <p>• <a href=\"https://cloudnext.withgoogle.com/speakers#target=fei-fei-li-348c6f60-441a-4edc-aaa3-5f59246b06c6\">Fei-Fei Li</a>, Chief Scientist, Cloud AI &amp; ML, Google Cloud</p> <p><b>Local Presentations  and Roundtable (19:30 - 20:30)</b></p> <p>Berkecz Ádám (AutSoft): </p> <p><b>Introduction to the Serverless Architecture</b></p> <p>Tömösvári Imre (AutSoft): </p> <p><b>Running microservices on Kubernetes</b></p> <p><b>Roundtable - Discussion with cloud Experts</b></p> <p>Moderator: Kassai Csaba - Big Data Engineer, Doctusoft - <a href=\"https://www.linkedin.com/in/csabakassai/\"><a href=\"https://www.linkedin.com/in/csabakassai/\" class=\"linkified\">https://www.linkedin.com/in/csabakassai/</a></a></p> <p>További vendégek: Tőzsér Tamás - CTO, Doctusoft, - <a href=\"https://www.linkedin.com/in/ttozser/\"><a href=\"https://www.linkedin.com/in/ttozser/\" class=\"linkified\">https://www.linkedin.com/in/ttozser/</a></a></p> <p><b>Streaming from SF. (20:30 - )  </b></p> <p>Cloud Next Official site: <a href=\"https://goo.gl/KfUWro\"><a href=\"https://goo.gl/KfUWro\" class=\"linkified\">https://goo.gl/KfUWro</a></a></p> <p>Further Cloud events: <a href=\"https://www.meetup.com/Big-Data-Meetup-Budapest/\">Budapest Big Data Meetup</a> has an Gogole Cloud Nexet Extended event on <a href=\"https://www.meetup.com/Big-Data-Meetup-Budapest/events/237902099/\">March 9.</a></p> <p>Sponsors of the event: <a href=\"https://goo.gl/1W3eO9\">Doctusoft</a>, <a href=\"https://goo.gl/u5li1y\">Skawa</a>, <a href=\"https://goo.gl/ICkh53\">BME Aut</a>, <a href=\"https://goo.gl/ItmkHF\">Reklámművek</a></p> ","visibility":"public"},{"created":1491203673000,"id":"238919905","name":"Infrastructure in da cloud","date_in_series_pattern":false,"status":"past","time":1492619400000,"local_date":"2017-04-19","local_time":"18:30","updated":1492679747000,"utc_offset":7200000,"waitlist_count":0,"yes_rsvp_count":77,"venue":{"id":24805142,"name":"A66","lat":47.507450103759766,"lon":19.066192626953125,"repinned":false,"address_1":"Andrássy út 66","city":"Budapest","country":"hu","localized_country_name":"Hungary"},"group":{"created":1356866254000,"name":"GDG Budapest","id":6397942,"join_mode":"open","lat":47.5099983215332,"lon":19.079999923706055,"urlname":"GDG-Budapest","who":"GDG Budapester","localized_location":"Budapest, Hungary","state":"","country":"hu","region":"en_US","timezone":"Europe/Budapest"},"link":"https://www.meetup.com/GDG-Budapest/events/238919905/","description":"<p>A következő meetupunk a felhő alapú infrastruktúrák jegyében telik majd. Ismét 3 előadást hallgathattok meg, utána pedig még a kötetlen networking előtt egy kb. 15 perces nyitott panelbeszélgetésre invitálunk titeket, ahol előadóinkat lehet kérdezni nagyjából bármiről! :)</p> <p><b>Az este előadói:</b></p> <p>1. <b>Meggyesi Zalán , Chief Support Engineer, Skawa Innovation Kft. </b><br/><a href=\"https://www.linkedin.com/in/zalan-meggyesi-aab00034/\" class=\"linkified\">https://www.linkedin.com/in/zalan-meggyesi-aab00034/</a></p> <p><b>Jenkins és Kubernetes: Skálázódó CI Google Alapokon: </b>Jenkins installáció migrálása GCE VM-ről GKE-re, a skálázódás és bővíthetőség érdekében. A VM-alapú CI installáció instabil lehet, egyetlen rendszer kiesése leállíthatja a teljes CI pipe-ot. Ezzel szemben a GKE-alapú Jenkins-raj hibatűrő és könnyen bővíthető további képességekkel, vagy skálázható a végtelenségbe. Az előadás során bemutatjuk a migráció lépéseit, egészen a klaszter indításától az utolsó simításokig a folyamatos futás előtt.</p> <p><b>2. Andorkó Balázs, Tech Lead; Szkiba Iván, Lead Architect; Udvari Tibor, Tech Lead - NNG /Services BU </b></p> <p><b>Container alapú microservice fejlesztés demo: </b>Container alapú microservice fejlesztési tapasztalatok Azure és GCP környezetben. Automatikus skálázás és rolling update élő bemutató.</p> <p><b>3. Gergely Pál Dávid, Google Solution Engineer, Doctusoft </b><br/><a href=\"https://www.linkedin.com/in/paldavidgergely/\" class=\"linkified\">https://www.linkedin.com/in/paldavidgergely/</a></p> <p><b>Amikor a konténerizáció nem feltétlenül a legjobb megoldás, akkor még ott az IaaS:  </b>A legtöbb alkalmazás esetén a konténerizáció nagyon jó (ha nem a legjobb) megoldás az éles környezetben való futtatásra. Azonban egy teljes webes szolgáltatás nyújtása nem áll meg csak az alkalmazás futtatásánál, hanem sokszor hozzá kapcsolódó adatbázisokra és egyéb infrastrukturális szolgáltatásokra is szükség van. Ezekre pedig a működésüknél fogva nem a legjobb megoldás a konténerizáció. Ugyan sokszor van lehetőség ezeket menedzselt formában igényelni a felhőszolgáltatótól, de előfordul, hogy ez nincs így és akkor marad a nagy fokú beállítási szabadsággal (és talán több munkával) kecsegtető IaaS vagyis virtuális gép szolgáltatás. Erre a felhasználási esetre szeretnék egy áttekintést adni és egy demón bemutatni a Google Compute Engine-en automatikusan skálázódó MongoDB cluster létrehozását.</p> <p><b>A panelbeszélgetés moderátora: </b><br/>Kassai Csaba, Data Architect, Doctusoft</p> <p><a href=\"https://www.linkedin.com/in/csabakassai/\" class=\"linkified\">https://www.linkedin.com/in/csabakassai/</a></p> <p>A helyszínt a Greenfox Academy-nek köszönhetjük, az esemény további támogatói pedig a Skawa Innovation és a Doctusoft.</p> ","visibility":"public"},{"created":1489815963000,"duration":104400000,"id":"238509776","name":"Google I/O Extended 2017 Budapest","date_in_series_pattern":false,"status":"past","time":1495033200000,"local_date":"2017-05-17","local_time":"17:00","updated":1495179973000,"utc_offset":7200000,"waitlist_count":0,"yes_rsvp_count":213,"venue":{"id":20728832,"name":"BME Q épület","lat":47.47251892089844,"lon":19.059730529785156,"repinned":false,"address_1":"Magyar Tudósok körútja 2. ","city":"Budapest","country":"hu","localized_country_name":"Hungary"},"group":{"created":1356866254000,"name":"GDG Budapest","id":6397942,"join_mode":"open","lat":47.5099983215332,"lon":19.079999923706055,"urlname":"GDG-Budapest","who":"GDG Budapester","localized_location":"Budapest, Hungary","state":"","country":"hu","region":"en_US","timezone":"Europe/Budapest"},"link":"https://www.meetup.com/GDG-Budapest/events/238509776/","description":"<p>Törj ki a keretekből a mobiloddal! -fókuszban a VR, 360 fokos kamera, DeX (Kenyeres Tamás - Samsung) </p> <p><b>[Update]:<br/></b>Stream: <a href=\"https://youtu.be/cRyi5crJRDU­ [Thursday's\" class=\"embedded\">https://youtu.be/cRyi5crJRDU­ [Thursday's</a> link]</p> <p>Videos:</p> <p>Latest Java 9 news (Imre Tömösvári- AutSoft): <a href=\"https://www.youtube.com/watch?v=6SlntePfboU\" class=\"embedded\">https://www.youtube.com/watch?v=6SlntePfboU</a><br/>Automatizált tesztelés hatékonyan (Mostoha Roland - AutSoft): <a href=\"https://www.youtube.com/watch?v=T639lKUykgE\" class=\"embedded\">https://www.youtube.com/watch?v=T639lKUykgE</a><br/>AppEngine a mindennapokban - Erősségek és buktatók (Farkas Péter - Doctusoft): <a href=\"https://www.youtube.com/watch?v=w4rEAVqWcuE\" class=\"embedded\">https://www.youtube.com/watch?v=w4rEAVqWcuE</a><br/>Demola Budapest bemutatkozás (Molnár Nikolett, Németh Bianka): <a href=\"https://www.youtube.com/watch?v=nysprtuLjYo\" class=\"embedded\">https://www.youtube.com/watch?v=nysprtuLjYo</a><br/>GEO adatbázis megoldások bemutatása (Szita Csongor - AutSoft): <a href=\"https://youtu.be/3nv18BlQOeQ?t=310\"><a href=\"https://youtu.be/3nv18BlQOeQ?t=310\" class=\"embedded\">https://youtu.be/3nv18BlQOeQ?t=310</a></a><br/>Composition over Inheritence Android környezetben (Balogh Tamás - AutSoft): <a href=\"https://youtu.be/3nv18BlQOeQ?t=1645\"><a href=\"https://youtu.be/3nv18BlQOeQ?t=1645\" class=\"embedded\">https://youtu.be/3nv18BlQOeQ?t=1645</a></a><br/>Google Cloud BigQuery (Berkecz Ádám - AutSoft): <a href=\"https://youtu.be/3nv18BlQOeQ?t=2994\"><a href=\"https://youtu.be/3nv18BlQOeQ?t=2994\" class=\"embedded\">https://youtu.be/3nv18BlQOeQ?t=2994</a></a></p> <p><b><br/></b></p> <p><b>[Hungarian]:</b></p> <p>A Budapesti Műszaki és Gazdaságtudományi Egyetem Villamosmérnöki és Informatika Karán, az Automatizálási és Alkalmazott Informatikai Tanszék (BME AUT) a GDG Budapesttel közösen idén is (immár ötödik alkalommal) megrendezi a Google I/O Extended eseményt. A rendezvény egy kiváló alkalom, mindazoknak akik első kézből szeretnének hallani a Google technológiai újdonságairól.</p> <p>Az esemény helyszíne a BME Q épülete: Budapest, Magyar tudósok körútja 2.</p> <p>Terem: QB402</p> <p><b>Várható kezdés május 17-én és 18-án 17 órától!</b></p> <p>A rendezvényen várhatóan élőben sugározzuk a legfontosabb előadásokat, valamint rengeteg érdekes és izgalmas téma kerül bemutatásra hazai fejlesztőktől és szakértőktől.</p> <p><b>Május 17.</b></p> <p>17:00 - 17:10: Megnyitó (Charaf Hassan - BME AUT)<br/>17:10 - 17:30: A Java 9 újdonságai (Tömösvári Imre - AutSoft)<br/>17:30 - 17:50: Automatizált tesztelés hatékonyan (Mostoha Roland - AutSoft)<br/>17:50 - 18:10: AppEngine a mindennapokban - Erősségek és buktatók (Farkas Péter - Doctusoft)<br/>18:10 - 18:20: Demola Budapest bemutatkozás (Molnár Nikolett, Németh Bianka)<br/>18:20 - 18:50: Törj ki a keretekből a mobiloddal! -fókuszban a VR, 360 fokos kamera, DeX (Kenyeres Tamás - Samsung)<br/>19:00 - 20:30: Keynote [Stream]<br/>20:30 - 21:00: Szünet<br/>21:00 - 21:20: GEO adatbázis megoldások bemutatása (Szita Csongor - AutSoft)<br/>21:20 - 21:40: Composition over Inheritence Android környezetben (Balogh Tamás - AutSoft)<br/>21:40 - 22:00: Google Cloud BigQuery (Berkecz Ádám - AutSoft)<br/>22:00 - 23:00: Developer Keynote</p> <p><b>Május 18.</b></p> <p>17:00 - 17:30: Van új az Android alatt: a legfrissebb layout technikák bemutatása (Gerlei Balázs - AutSoft)<br/>17:30 - 18:00: Ízelítő a Kotlin nyelvű Android fejlesztésből (Braun Márton - BME AUT)<br/>18:00 - 18:20: Network Coding a gyakorlatban (Braun Patrik - BME AUT)<br/>18:20 - 18:50: VR és AR a zsebedben - Zenfone AR bemutató (Gyepes Máté - Asus)<br/>18:50 - 19:10: Tesla technológia a Trabant kaszniban: korszerű webalkalmazások nem korszerű böngészőkön (Kozman Bálint - Ardinsys)<br/>19:10 - 19:30: Android API érdekességek - 2. rész (Ekler Péter - AutSoft)<br/>19:30 - 20:30: What's new in Android Support Library [Stream]<br/>20:30 - 21:30: Great Progressive Web App Experiences with Angular [Stream]<br/>21:30 - 22:30: What's possible with Cloud Functions for Firebase [Stream]</p> <p><b>[English]:</b></p> <p>The Department of Automation and Applied informatics at Budapest University of Technology and Economics (BME VIK AUT) and GDG Budapest organize Google I/O Extended for the fifth time. The event is a good opportunity to get to know the latest technology news from Google and also to meet with local developer communities.</p> <p>Location: BME, building Q, Magyar tudósok körútja 2., room QB402</p> <p>Start time: 5 pm, May 17 -18</p> <p>Come and attend the most important Google I/O presentations via live stream and a lot of interesting and exciting topics presented by local professionals.</p> <p>Agenda</p> <p><b>17 May</b></p> <p>17:00 - 17:10: Opening (Hassan Charaf - BME AUT)<br/>17:10 - 17:30: Latest Java 9 news (Imre Tömösvári- AutSoft)<br/>17:30 - 17:50: Effective automated testing in Android (Roland Mostoha - AutSoft)<br/>17:50 - 18:10: Using AppEngine - Strengths &amp; Difficulties (Péter Farkas - Doctusoft)<br/>18:10 - 18:20: Introduction of Demola Budapest (Nikolett Molnár, Bianka Németh)<br/>18:20 - 18:50: Push the limits with your cell phone! -VR, 360 degree camera in focus (Tamás Kenyeres- Samsung)<br/>19:00 - 20:30: Keynote [Stream]<br/>20:30 - 21:00: Coffee break<br/>21:00 - 21:20: Introduction to GEO database technologies (Csongor Szita - AutSoft)<br/>21:20 - 21:40: Composition over Inheritance in Android – (Tamás Balogh - AutSoft)<br/>21:40 - 22:00: Google Cloud BigQuery (Ádám Berkecz - AutSoft)<br/>22:00 - 23:00: Developer Keynote</p> <p><b>18 May</b></p> <p>17:00 - 17:30: The newest layout techniques in Android (Balázs Gerlei - AutSoft)<br/>17:30 - 18:00: Introduction to Kotlin (Márton Braun - BME AUT)<br/>18:00 - 18:20: Network Coding in practice (Patrik Braun - BME AUT)<br/>18:20 - 18:50: VR and AR in your pockets- Zenfone AR presentation (Máté Gyepes - Asus)<br/>18:50 - 19:10: Tesla technolgy in \"Trabant\" environment: modern web applications on old browsers (Bálint Kozman - Ardinsys)<br/>19:10 - 19:30: Discovering the Android API - Part 2 (Péter Ekler - AutSoft)<br/>19:30 - 20:30: What's new in Android Support Library [Stream]<br/>20:30 - 21:30: Great Progressive Web App Experiences with Angular [Stream]<br/>21:30 - 22:30: What's possible with Cloud Functions for Firebase [Stream]</p> ","how_to_find_us":"BME Q épület, QB402","visibility":"public"},{"created":1495458326000,"id":"240179372","name":"Join the Dart side!","date_in_series_pattern":false,"status":"past","time":1496939400000,"local_date":"2017-06-08","local_time":"18:30","updated":1497969577000,"utc_offset":7200000,"waitlist_count":0,"yes_rsvp_count":42,"venue":{"id":25256583,"name":"Lónyay Irodaház alsó szint, nagyterem","lat":47.484256744384766,"lon":19.062847137451172,"repinned":false,"address_1":"1093 Budapest, Lónyay u. 31. ","city":"Budapest","country":"hu","localized_country_name":"Hungary"},"group":{"created":1356866254000,"name":"GDG Budapest","id":6397942,"join_mode":"open","lat":47.5099983215332,"lon":19.079999923706055,"urlname":"GDG-Budapest","who":"GDG Budapester","localized_location":"Budapest, Hungary","state":"","country":"hu","region":"en_US","timezone":"Europe/Budapest"},"link":"https://www.meetup.com/GDG-Budapest/events/240179372/","description":"<p>A Google <b>Dart programozási nyelvét</b> fogjuk boncolgatni, kliens és szerver oldali alkalmazásába adunk betekintőt.</p> <p>A Dart egy aktívan fejlesztett általános programozási nyelv, speciális fókusszal a webre. Olyan hatalmas alkalmazásokat írnak benne, mint amilyen az AdWords és AdSense, melyeken dollármilliárdok folynak át évente.</p> <p>A meetup során igyekszünk ízelítőt adni arról, hogy a Dartnak milyen felhasználási lehetőségei vannak - illetve mi mire használjuk.</p> <p>Az előadások után egy panelbeszélgetésre invitálunk, mely során a kérdezők között 3D nyomtatott ajándékokat sorsolunk ki.</p> <p><b>Előadóink: </b></p> <p><b>1. Skálázható alkalmazások Dart nyelven Google infrastruktúrán</b></p> <p><b>Siroki Péter, Lead Architect- Skawa Innovation</b>  </p> <p>A Google App Engine Flex segítségével végre lehetőség nyílik arra, hogy Dartban fejlesszünk skálázható webalkalmazásokat. Az előadásban bemutatom a Google App Engine környezetet, a Datastore sajátosságait és egy pár hasznos libraryt, amivel az adatelérés egyszerűbbé tehető.</p> <p><b>2/1. Progressive Web App: átmenet a mobil és a web világ között</b></p> <p><b>Soós István </b></p> <p>Offline web alkalmazások, push notification, Add to Home screen funkció az elméletben és a gyakorlatban. A szabvány és az arra épülő Dart library bemutatása gyakorlati példákon keresztül.</p> <p><b>3.  Angular 2 Dart - tippek, trükkök, nem csak Dartosoknak</b></p> <p><b>Varga-Háli Dániel, Lead Front-end Developer- Skawa Innovation</b></p> <p>A TodoMVC-n túl: hogyan maradjon a kliens oldali alkalmazásunk moduláris, performens és őrizzük meg a teljesítményét.</p> <p>Mire figyeljünk oda, amikor komponenseket készítünk, vagy éppen a 100. `@Injectable()`-t.</p> <p><b>2/2. Dart VM tapasztalatok: async, isolate, GC</b></p> <p><b>Soós István</b></p> <p>Tippek és trükkök nagyobb szerver-oldali programokhoz: hogyan párhuzamosítsuk az adatbázis-műveleteket és hogyan adjunk rate limitert bizonyos funkciókhoz.</p> <p>Az előadásokról és a panelbeszélgetésről élő közvetítés készül, melyet az alábbi oldalakon kísérhettek figyelemmel:</p> <p><a href=\"https://www.youtube.com/user/gdgbudapest\">GDG Budapest YouTube oldal</a></p> <p><a href=\"https://www.facebook.com/groups/1832714317053666/?ref=group_browse_new\">GDG Budapest Facebook csoport</a></p> <p>Az esemény támogatója a Doctusoft és a Skawa Innovation, a helyszínt a Skawa biztosítja.</p> ","visibility":"public"},{"created":1495785428000,"id":"240288715","name":"Android - hatékonyan (sorozat), 2. alkalom","date_in_series_pattern":false,"status":"past","time":1498752000000,"local_date":"2017-06-29","local_time":"18:00","updated":1498862940000,"utc_offset":7200000,"waitlist_count":0,"yes_rsvp_count":81,"venue":{"id":20728832,"name":"BME Q épület","lat":47.47251892089844,"lon":19.059730529785156,"repinned":false,"address_1":"Magyar Tudósok körútja 2. ","city":"Budapest","country":"hu","localized_country_name":"Hungary"},"group":{"created":1356866254000,"name":"GDG Budapest","id":6397942,"join_mode":"open","lat":47.5099983215332,"lon":19.079999923706055,"urlname":"GDG-Budapest","who":"GDG Budapester","localized_location":"Budapest, Hungary","state":"","country":"hu","region":"en_US","timezone":"Europe/Budapest"},"link":"https://www.meetup.com/GDG-Budapest/events/240288715/","description":"<p><b>TEREM VÁLTOZÁS: QB402 (4. emelet, tetőterasz mellett, ahol a Google I/O Extended is volt)</b></p> <p>BME Q, QB402</p> <p>Tervezett témák:</p> <p>- Rövid beszámoló a Google I/O-ról (Maczkó István)<br/>- Kotlin a gyarkorlatban (Balogh Tamás)<br/>- Single-Activity alkalmazások tervezése Fragment-ek nélkül (Váradi Gábor)<br/>- Alkalmazás Architektúra Komponensek (Ekler Péter)</p> <p>---------------</p> <p>Topics:<br/>- Google I/O Summary (István Maczkó)<br/>- Kotlin in practice (Tamás Balogh)<br/>- Architecting Single-Activity apps without Fragments (Gábor Váradi)<br/>- Application Architecture Components (Péter Ekler)</p> ","visibility":"public"},{"created":1502272867000,"duration":32400000,"id":"242404364","name":"DevFest - Budapest 2017","date_in_series_pattern":false,"status":"past","time":1507617000000,"local_date":"2017-10-10","local_time":"08:30","updated":1518448725000,"utc_offset":7200000,"waitlist_count":0,"yes_rsvp_count":75,"venue":{"id":25417168,"name":"Hotel Benczúr","lat":47.51164245605469,"lon":19.076658248901367,"repinned":false,"address_1":" Benczúr u. 35","city":"Budapest","country":"hu","localized_country_name":"Hungary"},"group":{"created":1356866254000,"name":"GDG Budapest","id":6397942,"join_mode":"open","lat":47.5099983215332,"lon":19.079999923706055,"urlname":"GDG-Budapest","who":"GDG Budapester","localized_location":"Budapest, Hungary","state":"","country":"hu","region":"en_US","timezone":"Europe/Budapest"},"link":"https://www.meetup.com/GDG-Budapest/events/242404364/","manual_attendance_count":80,"description":"<p>GDG DevFest 2017 is our annual all-day developer conference that offers speaker sessions across multiple product areas, codelabs, hackathon (planned) more!</p> <p><b>This is a not for profit event</b> - however we have to cover venue and catering cost, and we limited the number of the sponsors to keep our freedom to chose the hottest topics. This is the reason we collect a small fee (if anyone interested on our budget, just contact me, I am ready to share details to help other groups to organize similar events) .</p> <p><b>Tickets are available on Eventbrite:</b><a href=\"https://goo.gl/a55M7u\"> <a href=\"https://goo.gl/a55M7u\" class=\"linkified\">https://goo.gl/a55M7u</a></a><br/><b>Tickets enquiry form:</b> <a href=\"https://goo.gl/83Xvmu\"><a href=\"https://goo.gl/83Xvmu\" class=\"linkified\">https://goo.gl/83Xvmu</a></a> (if you want to buy more tickets, or pay by bank transfer, or have any questions)<br/><b>Tickest also available at:</b><br/>G.M. Production Kft.<br/>1034 Bp. Bécsi u. 100.<br/>Tel.: [masked]  (workdays 9:00-16:00)<br/>[masked]</p> <p><b>Fees include buffet lunch, softdrinks and snacks.</b></p> <p>This meetup is for reporting purposes only, we use a different ticketing system.</p> <p><b>Registration starts: 8:30</b></p> <p><b>9:00 - 10:40</b><br/>Kassai Csaba (DoctuSoft) - Building a Data Warehouse in the Google Cloud<br/>Tőzsér Tamás (DoctuSoft) - Why should Spanner excite you?<br/>Kocsis Márk - Google APIs for business purposes</p> <p><b>10:40- 11:00</b> coffee break</p> <p><b>11:00-12:10</b><br/>Balogh Tamás (AutSoft) - Secure Android Applications - What a developer must care about<br/>Danny Preussler – ViewModel and Architecture Components </p> <p><b>12:</b><b>10-13:00</b> Lunch</p> <p><b>13:00-14:10</b><br/>Polacsek Attila  (Supercharge) Android and Flux: It's a match!<br/>Daniele Bonaldo - Build a clock that writes you the time with Android Things</p> <p><b>14:10:14:30 </b>coffee break</p> <p><b>14:30-16:10</b><br/><i>Bob van Luijt - A Semantic Internet of Things - (Update: unfortunately could not come)</i><br/>Geurts Dennis -  Android Things - Peripheral I/O<br/>Balázs Gerlei (AutSoft ) - Flutter - true cross-plaform solution or just a tool for prototyping?</p> <p><b>16:10-16:30</b> Break</p> <p><b>16:30-17:40</b><br/>Nik Page – User Experience Strategy</p> <p>Sipos Gergely (DoctuSoft) - Angular 2+ components with RxJS</p> <p><b>9:00 - 17:00</b><br/>Codelabs<br/>Bring Your computer and try Google Codelabs: <a href=\"https://goo.gl/johU5w\"><a href=\"https://goo.gl/johU5w\" class=\"linkified\">https://goo.gl/johU5w</a></a></p> <p>Some of our Speakers: <br/><b>Dannyi Preusler, Google Developer Expert</b>, <a href=\"https://goo.gl/ZsmUNh\"><a href=\"https://goo.gl/ZsmUNh\" class=\"linkified\">https://goo.gl/ZsmUNh</a></a><br/><b>Nik Page, Google Developer Expert</b>, <a href=\"https://goo.gl/rKyKCt\"><a href=\"https://goo.gl/rKyKCt\" class=\"linkified\">https://goo.gl/rKyKCt</a></a></p> <p><a href=\"https://devfest.gdg-budapest.com/\"><a href=\"https://devfest.gdg-budapest.com/\" class=\"linkified\">https://devfest.gdg-budapest.com/</a></a></p> <p>Tags: </p> <p>android,  android studio, kotlin, cloud, compute engine, app engine, GCP, Google Cloud, Google Cloud Platform, <br/> backend, architecture, Big Query, BQ, <br/>App Engine, GAE, firebase, gde, android things, weave, cloud iot, devkit, dev kit, iot, codelab, hackathon, devfest, appfest,  DevFest</p> ","visibility":"public"},{"created":1514734882000,"duration":10800000,"id":"246349364","name":"2018 Évindító - Tervek 2018-ra","rsvp_limit":12,"date_in_series_pattern":false,"status":"past","time":1515517200000,"local_date":"2018-01-09","local_time":"18:00","updated":1518448667000,"utc_offset":3600000,"waitlist_count":0,"yes_rsvp_count":7,"venue":{"id":24342244,"name":"Murok Cafe","lat":47.5147705078125,"lon":19.035663604736328,"repinned":false,"address_1":"Török utca 2","city":"Budapest","country":"hu","localized_country_name":"Hungary"},"group":{"created":1356866254000,"name":"GDG Budapest","id":6397942,"join_mode":"open","lat":47.5099983215332,"lon":19.079999923706055,"urlname":"GDG-Budapest","who":"GDG Budapester","localized_location":"Budapest, Hungary","state":"","country":"hu","region":"en_US","timezone":"Europe/Budapest"},"link":"https://www.meetup.com/GDG-Budapest/events/246349364/","manual_attendance_count":20,"description":"<p>2018 Évindító</p> <p>• Első félév meetup témák, előadók</p> <p>• Szervezők, új szervezőket is keresünk</p> ","visibility":"public"},{"created":1519858730000,"duration":21600000,"id":"248277054","name":"Google I/O Extended 2018 Budapest","date_in_series_pattern":false,"status":"past","time":1525791600000,"local_date":"2018-05-08","local_time":"17:00","updated":1527024127000,"utc_offset":7200000,"waitlist_count":0,"yes_rsvp_count":147,"venue":{"id":20728832,"name":"BME Q épület","lat":47.47251892089844,"lon":19.059730529785156,"repinned":false,"address_1":"Magyar Tudósok körútja 2. ","city":"Budapest","country":"hu","localized_country_name":"Hungary"},"group":{"created":1356866254000,"name":"GDG Budapest","id":6397942,"join_mode":"open","lat":47.5099983215332,"lon":19.079999923706055,"urlname":"GDG-Budapest","who":"GDG Budapester","localized_location":"Budapest, Hungary","state":"","country":"hu","region":"en_US","timezone":"Europe/Budapest"},"link":"https://www.meetup.com/GDG-Budapest/events/248277054/","manual_attendance_count":75,"description":"<p>[Hungarian]:</p> <p>A Budapesti Műszaki és Gazdaságtudományi Egyetem Villamosmérnöki és Informatika Karán, az Automatizálási és Alkalmazott Informatikai Tanszék (BME AUT) a GDG Budapesttel közösen idén is (immár hatodik alkalommal) megrendezi a Google I/O Extended eseményt. A rendezvény egy kiváló alkalom mindazoknak, akik első kézből szeretnének hallani a Google technológiai újdonságairól.</p> <p>Az esemény helyszíne a BME Q épülete, QB402: Budapest, Magyar tudósok körútja 2.</p> <p>Várható kezdés május 8-án 17 órától!</p> <p>A rendezvényen várhatóan élőben sugározzuk a legfontosabb előadásokat, valamint rengeteg érdekes és izgalmas téma kerül bemutatásra hazai fejlesztőktől és szakértőktől.</p> <p>Május 8.</p> <p>17:00-17:05: Megnyitó<br/>17:05-17:15: Demola bemutató<br/>17:15-17:30: Chrome V8 a gépháztető alatt (Tömösvári Imre - AutSoft)<br/>17:30-18:00: Blockchain és társai (Ott Károly - MOL)<br/>18:00-18:30: Az Antenna Hungária Zrt a Drukka Startup Stúdió együttműködésével elindította Magyarország első hardware vállalati akcelerátor programját (Radák Bence - Drukka)<br/>18:30-19:00: Hogyan debuggoljuk a felhőt? (Vicze Zsolt - Doctusoft)<br/>19:00-20:30: Keynote<br/>20:50-21:20: Top 10 Kotlin Stack Overflow kérdés (Braun Márton - AutSoft)<br/>21:20-21:45: Adatbetöltés laponként és egyszerűen Android platformon (AAC Paging Library) (Váradi Gábor)<br/>21:45-23:00: Developer keynote</p> <p>[English]:</p> <p>The Department of Automation and Applied informatics at Budapest University of Technology and Economics (BME VIK AUT) and GDG Budapest organize Google I/O Extended for the sixth time. The event is a good opportunity to get to know the latest technology news from Google and also to meet local developer communities.</p> <p>Location: BME, building Q, Magyar tudósok körútja 2. Room QB402</p> <p>Start time: 5 pm, May 8</p> <p>Come and attend the most important Google I/O presentations via live stream and a lot of interesting and exciting topics presented by local professionals.</p> <p>Agenda</p> <p>8 May</p> <p>17:00 - 17:05: Opening<br/>17:05 - 17:15: Demola introduction<br/>17:15-17:30: Chrome V8 Under the Hood (Imre Tömösvári - AutSoft)<br/>17:30-18:00: Blockchain and Co. (Károly Ott - MOL)<br/>18:00-18:30: Antenna Hungaria Zrt with the cooperation of Drukka Startup Studio has introduced Hungary’s first hardware corporate accelarator program (Bence Radák - Drukka)<br/>18:30-19:00: How to debug the cloud? (Zsolt Vicze - Doctusoft)<br/>19:00-20:30: Keynote<br/>20:50-21:20: Top 10 Kotlin Stack Overflow questions (Márton Braun - AutSoft)<br/>21:20-21:45: Paging Like a Pro (Android Paging Library) (Gábor Váradi)<br/>21:45-23:00: Developer keynote</p> ","how_to_find_us":"BME Q épület, QB402","visibility":"public"},{"created":1530275417000,"duration":9000000,"id":"252269857","name":"Google Assistant","rsvp_limit":50,"date_in_series_pattern":false,"status":"past","time":1534437000000,"local_date":"2018-08-16","local_time":"18:30","updated":1535462316000,"utc_offset":7200000,"waitlist_count":0,"yes_rsvp_count":50,"venue":{"id":25694039,"name":"Up center Budapest","lat":47.479835510253906,"lon":19.051063537597656,"repinned":false,"address_1":"1114 Bartók Béla út 29. ","city":"Budapest","country":"hu","localized_country_name":"Hungary"},"group":{"created":1356866254000,"name":"GDG Budapest","id":6397942,"join_mode":"open","lat":47.5099983215332,"lon":19.079999923706055,"urlname":"GDG-Budapest","who":"GDG Budapester","localized_location":"Budapest, Hungary","state":"","country":"hu","region":"en_US","timezone":"Europe/Budapest"},"link":"https://www.meetup.com/GDG-Budapest/events/252269857/","manual_attendance_count":12,"description":"<p>Actions on Google and Google Assistant are one of the major Google technical areas and we want to invite the whole developer community to learn about creating Actions for the Google Assistant.<br/>Build Actions for Your Community - #buildactionsforyourcommunity</p> <p>Actions Showcase !!!<br/>Bring your Actions to the Meetup.<br/>THE CODER OF THE BEST ACTION WILL GET A GOOGLE AIY VOICE KIT!</p> <p>Presentations</p> <p>Google Assistant voice UX - Presentation via Google Hangout<br/>Adi Mazor Kairo - Google Developer Expert<br/><a href=\"https://www.linkedin.com/in/adimazorkario/\" class=\"linkified\">https://www.linkedin.com/in/adimazorkario/</a></p> <p>First Steps with Google Assistant - Experiences with Codelab<br/>Yahya Azouzi<br/><a href=\"https://www.linkedin.com/in/yahya-azouzi-202169b4/\" class=\"linkified\">https://www.linkedin.com/in/yahya-azouzi-202169b4/</a></p> <p>Some URL to start you first Actions:<br/>Intro Video:<br/><a href=\"https://www.youtube.com/watch?v=QN2x8yg92Yc\" class=\"embedded\">https://www.youtube.com/watch?v=QN2x8yg92Yc</a></p> <p>Actions Page:<br/><a href=\"https://assistant.google.com/services/invoke?hl=en\" class=\"linkified\">https://assistant.google.com/services/invoke?hl=en</a></p> <p>Extending the Assistant:<br/><a href=\"https://developers.google.com/actions/extending-the-assistant\" class=\"linkified\">https://developers.google.com/actions/extending-the-assistant</a></p> <p>Actions on Google - The Platform:<br/><a href=\"https://console.actions.google.com/?pli=1\" class=\"linkified\">https://console.actions.google.com/?pli=1</a></p> <p>“Build Actions for Your Community” Developer Webinar May 16th (9am PST)<br/><a href=\"https://www.youtube.com/watch?v=0kKK4Wzx820\" class=\"embedded\">https://www.youtube.com/watch?v=0kKK4Wzx820</a></p> <p>Google AIY Voice Kit:<br/><a href=\"https://aiyprojects.withgoogle.com/voice/\" class=\"linkified\">https://aiyprojects.withgoogle.com/voice/</a></p> <p>The event is free<br/>Sponsored by Google and Reklámművek</p> ","how_to_find_us":"The entrance is at the side building (not directly from Bartok Bela u)","visibility":"public"},{"created":1542915686000,"duration":7200000,"id":"256630340","name":"GDG Budapest - November","rsvp_limit":20,"date_in_series_pattern":false,"status":"past","time":1543510800000,"local_date":"2018-11-29","local_time":"18:00","updated":1544472045000,"utc_offset":3600000,"waitlist_count":0,"yes_rsvp_count":14,"venue":{"id":25999268,"name":"Reklámművek - LHT Irodaház","lat":47.53461837768555,"lon":19.034076690673828,"repinned":false,"address_1":"Bécsi út 100","address_2":"I. em. 5","city":"Budapest","country":"hu","localized_country_name":"Hungary"},"group":{"created":1356866254000,"name":"GDG Budapest","id":6397942,"join_mode":"open","lat":47.5099983215332,"lon":19.079999923706055,"urlname":"GDG-Budapest","who":"GDG Budapester","localized_location":"Budapest, Hungary","state":"","country":"hu","region":"en_US","timezone":"Europe/Budapest"},"link":"https://www.meetup.com/GDG-Budapest/events/256630340/","manual_attendance_count":5,"description":"<p>Beszélgetés, Pizza stb.<br/>Machine Learning<br/>Apps Script<br/>App Engine</p> ","visibility":"public"},{"created":1543943982000,"duration":5400000,"id":"256943970","name":"Wesley Chun - Google Developer Advocate - Drink a beer :-) - LIMITED space!","rsvp_limit":12,"date_in_series_pattern":false,"status":"past","time":1544628600000,"local_date":"2018-12-12","local_time":"16:30","updated":1544808203000,"utc_offset":3600000,"waitlist_count":0,"yes_rsvp_count":10,"venue":{"id":23002782,"name":"Hadik kávéház","lat":47.47909164428711,"lon":19.050870895385742,"repinned":false,"address_1":"Bartók Béla út 36.","city":"Budapest","country":"hu","localized_country_name":"Hungary"},"group":{"created":1356866254000,"name":"GDG Budapest","id":6397942,"join_mode":"open","lat":47.5099983215332,"lon":19.079999923706055,"urlname":"GDG-Budapest","who":"GDG Budapester","localized_location":"Budapest, Hungary","state":"","country":"hu","region":"en_US","timezone":"Europe/Budapest"},"link":"https://www.meetup.com/GDG-Budapest/events/256943970/","manual_attendance_count":5,"description":"<p>\"I am Wesley Chun, a Developer Advocate for Google who will be visiting Budapest in a few weeks (Dec 11-13). I'm looking to connect with local Google developers in the area and would be open to speaking about Google Cloud (GCP and/or G Suite developer tools).\"<br/>\"Here are my most recent talks from Cloud NEXT '18, which will be similar to what I will do:<br/>1) G Suite APIs: cloud.withgoogle.com/next18/sf/sessions/session/201086<br/>2) GCP+G Suite: cloud.withgoogle.com/next18/sf/sessions/session/156878\"</p> <p>He also wrote some books :-)<br/><a href=\"https://www.linkedin.com/in/wesleychun\" class=\"linkified\">https://www.linkedin.com/in/wesleychun</a></p> <p>There will be no presentation this day. Just a nice chat, some beer and meeting with clever guys.</p> <p>As it is a last minute organized event, we have limited space, so if you could not come, please set your answer for NOT coming!</p> <p>It is not a sponsored event, so you pay for your consumption (if any).</p> ","visibility":"public"},{"created":1550571664000,"duration":19800000,"id":"259087458","name":"Hash Code team programming competition organized by Google","rsvp_limit":50,"date_in_series_pattern":false,"status":"past","time":1551371400000,"local_date":"2019-02-28","local_time":"17:30","updated":1551394036000,"utc_offset":3600000,"waitlist_count":0,"yes_rsvp_count":20,"venue":{"id":26190177,"name":"Schönherz Kollégium","lat":47.472904205322266,"lon":19.05324363708496,"repinned":true,"address_1":"Irinyi József u. 42","city":"Budapest","country":"hu","localized_country_name":"Hungary"},"group":{"created":1356866254000,"name":"GDG Budapest","id":6397942,"join_mode":"open","lat":47.5099983215332,"lon":19.079999923706055,"urlname":"GDG-Budapest","who":"GDG Budapester","localized_location":"Budapest, Hungary","state":"","country":"hu","region":"en_US","timezone":"Europe/Budapest"},"link":"https://www.meetup.com/GDG-Budapest/events/259087458/","description":"<p>Think you could optimize the layout of a Google Data Center? How about scheduling a fleet of drones to make deliveries around the world? Tackle an engineering problem from Google during Hash Code, our team programming competition. Are you up for the challenge?</p> <p>Hash Code 2019: <a href=\"http://g.co/hashcode\" class=\"linkified\">http://g.co/hashcode</a></p> <p>&gt;&gt;&gt; IMPORTANT: Don't forget to register by Monday, 25th February &lt;&lt;&lt;</p> <p>What’s involved?</p> <p>Hash Code is a team programming competition, organized by Google, for students and professionals around the world. You pick your team and programming language and we pick an engineering problem for you to solve. This year’s contest kicks off with an Online Qualification Round, where your team can compete from the Budapest Hash Code hub. Top teams will then be invited to a Google office for the Final Round.</p> <p>What is Hash Code?</p> <p>Google’s team-based programming competition, Hash Code, allows you to share your skills and connect with other coders as you work together to solve a problem modeled off a real Google engineering challenge! In small teams of two to four, coders all over the world will tackle the first problem through an Online Qualification Round. The top teams from this round are invited to join us at an international Google office for our annual Hash Code Final Round.</p> <p>How it works?</p> <p>Once you’ve registered for the contest, you’ll gain access to our Judge System. The Judge System is our online platform where you’ll form your team, join a hub, practice, and compete during the rounds. During the Online Qualification Round, you’ll watch our YouTube livestream to be introduced to the problem, and your team will have four hours to solve an optimization problem using the programming language and tools of your choice. The top teams from the Online Qualification Round will be invited to the Final Round at a Google office, where they’ll work together to solve another challenge and compete for cash prizes.</p> <p>Prize (Final Round)</p> <p>1st Place: $4,000 USD<br/>2nd Place: $2,000 USD<br/>3rd Place: $1,000 USD</p> <p>The Budapest hub</p> <p>GDG Budapest &amp; KSZK has setup a Hub in Budapest called \"GDG Budapest - Schönherz KSZK Hub\" for contestants based in Hungary.</p> <p>Location: Schönherz Kollégium, 1117 Budapest, Irinyi József u. 42.</p> <p>How do I join the Budapest hub?</p> <p>Select the \"GDG Budapest - Schönherz KSZK Hub\" in the “My Team” section of the Judge System at <a href=\"https://hashcodejudge.withgoogle.com\" class=\"linkified\">https://hashcodejudge.withgoogle.com</a></p> <p>Rules</p> <p>Please read carefully the Terms and Conditions, Google’s general Privacy Policy, and these rules for Hash Code 2019 described under the below link</p> <p><a href=\"https://codingcompetitions.withgoogle.com/hashcode/rulesandterms\" class=\"linkified\">https://codingcompetitions.withgoogle.com/hashcode/rulesandterms</a></p> <p>Frequently Asked Questions</p> <p><a href=\"https://codingcompetitions.withgoogle.com/hashcode/faq\" class=\"linkified\">https://codingcompetitions.withgoogle.com/hashcode/faq</a></p> <p>Schedule</p> <p>Feb 25, 2019 - Hash Code online registration closes<br/>Feb 28, 2019 - Online qualification round @ Budapest Hub<br/>Apr 27, 2019 - Final round @ Google Dublin Offices</p> <p><a href=\"https://codingcompetitions.withgoogle.com/hashcode/schedule\" class=\"linkified\">https://codingcompetitions.withgoogle.com/hashcode/schedule</a></p> <p>Registration</p> <p>&gt;&gt;&gt; Register to this meetup ONLY if you are contestant of the Hash Code programming competition AND if you are planning to participate Hash Code Online Qualification Round from the \"GDG Budapest - Schönherz KSZK Hub\" &lt;&lt;&lt;</p> <p>Contact</p> <p>Should you have any questions regarding this meetup or attending Hash Code from the Budapest Hub, turn to the organizer at</p> <p>Email: [masked]<br/>Twitter: @GDGBud @zptoth</p> <p>Links</p> <p><a href=\"https://g.co/hashcode\" class=\"linkified\">https://g.co/hashcode</a><br/><a href=\"https://fb.com/events/268938510672903\" class=\"linkified\">https://fb.com/events/268938510672903</a><br/><a href=\"https://fb.com/GDG.Budapest\" class=\"linkified\">https://fb.com/GDG.Budapest</a><br/><a href=\"https://twitter.com/GDGBud\" class=\"linkified\">https://twitter.com/GDGBud</a><br/><a href=\"https://kszk.sch.bme.hu\" class=\"linkified\">https://kszk.sch.bme.hu</a></p> ","how_to_find_us":"You will find us ;-)","visibility":"public"},{"created":1550004818000,"duration":12600000,"id":"258907883","name":"2019 TensorFlow DevSummit viewing party & meetup at Google Hungary, TF DevSummit","rsvp_limit":21,"date_in_series_pattern":false,"status":"past","time":1551886200000,"local_date":"2019-03-06","local_time":"16:30","updated":1551903972000,"utc_offset":3600000,"waitlist_count":0,"yes_rsvp_count":21,"venue":{"id":26225713,"name":"Óbuda Gate Irodaház","lat":47.52398681640625,"lon":19.038625717163086,"repinned":true,"address_1":"Dara u. 1","city":"Budapest","country":"hu","localized_country_name":"Hungary"},"group":{"created":1356866254000,"name":"GDG Budapest","id":6397942,"join_mode":"open","lat":47.5099983215332,"lon":19.079999923706055,"urlname":"GDG-Budapest","who":"GDG Budapester","localized_location":"Budapest, Hungary","state":"","country":"hu","region":"en_US","timezone":"Europe/Budapest"},"link":"https://www.meetup.com/GDG-Budapest/events/258907883/","description":"<p>Join the geekest machine learning enthusiasts on March 6 at the Google office in Budapest.</p> <p>TensorFlow Dev Summit brings together a diverse mix of machine learning users from around the world for two days of highly technical talks, demos, and conversation with the TensorFlow team and community.</p> <p>The annual TensorFlow DevSummit takes place on March 6-7, 2019 in the Google Event Center, Sunnyvale, California USA.</p> <p><a href=\"https://www.tensorflow.org/dev-summit\" class=\"linkified\">https://www.tensorflow.org/dev-summit</a></p> <p>Let's watch together the video/livestream of the 2019 TensorFlow Dev Summit from the Google office in Budapest and discuss machine learning.</p> <p>As a warmup before the livestream, Kornel Regius (Google Hungary) will talk about the work of Google employees in Hungary.</p> <p>He will be followed by Norbert Liki (Data Science Architect @ Aliz) with a presentation: News recommendation with Tensorflow</p> <p>A brief description of his presentation:</p> <p>Use of recommendation systems is widespread in many places now. In this talk I will show a use case for news recommendations using Tensorflow. Concentrating on the main building blocks and how you can deploy it on Google Cloud Platform.</p> <p>The number of attendees is limited to 20.</p> <p>Don't miss this rare occasion where you will have the opportunity to<br/>- visit Google office in Hungary<br/>- talk to a Googler<br/>- meet fellow GDG Budapest members and machine learning experts.</p> <p>Location:<br/>- Google Hungary - Óbuda Gate Irodaház, 1023 Budapest, Dara u. 1.</p> <p>Event sponsors:<br/>- Google Hungary - www.google.hu<br/>- Reklámművek - G.M. Production Kft - www.reklammuvek.com<br/>- Aliz - www.aliz.ai</p> <p>About TensorFlow</p> <p>TensorFlow™ is an open source software library for high performance numerical computation. Its flexible architecture allows easy deployment of computation across a variety of platforms (CPUs, GPUs, TPUs), and from desktops to clusters of servers to mobile and edge devices. Originally developed by researchers and engineers from the Google Brain team within Google’s AI organization, it comes with strong support for machine learning and deep learning and the flexible numerical computation core is used across many other scientific domains.</p> <p><a href=\"https://www.tensorflow.org\" class=\"linkified\">https://www.tensorflow.org</a></p> <p>Follow GDG Budapest on social media</p> <p><a href=\"https://instagram.com/gdgbudapest\" class=\"linkified\">https://instagram.com/gdgbudapest</a><br/><a href=\"https://facebook.com/GDG.Budapest\" class=\"linkified\">https://facebook.com/GDG.Budapest</a><br/><a href=\"https://twitter.com/GDGBud\" class=\"linkified\">https://twitter.com/GDGBud</a><br/><a href=\"https://meetup.com/GDG-Budapest\" class=\"linkified\">https://meetup.com/GDG-Budapest</a></p> <p>#TFDevSummit #GDG #GDGBudapest</p> ","how_to_find_us":"Óbuda Gate office building - Data u. Entrance - 5th floor (5. emelet) ","visibility":"public"}],"organizers":[{"id":46033482,"name":"István M.","bio":"Co-founder  of Yappp.\nDigital Marketing Entrepreneur. Specialties: Social Media and Advertisement management, Social Media and Advertisement Platform development, Data Analysis.","status":"active","joined":1335515443000,"city":"Budapest","country":"hu","localized_country_name":"Hungary","lat":47.51,"lon":19.08,"photo":{"id":88940402,"photo_link":"https://secure.meetupstatic.com/photos/member/4/f/b/2/member_88940402.jpeg","thumb_link":"https://secure.meetupstatic.com/photos/member/4/f/b/2/thumb_88940402.jpeg","type":"member","base_url":"https://secure.meetupstatic.com"},"group_profile":{"status":"active","visited":1554385446000,"created":1357219146000,"updated":1375438900000,"role":"organizer","group":{"id":6397942,"urlname":"GDG-Budapest","name":"GDG Budapest","status":"active","who":"GDG Budapester","members":1203,"join_mode":"open","localized_location":"Budapest, Hungary"},"answers":[{"question_id":3263842,"question":"What Google technologies are you using?","answer":"Apps script"},{"question_id":3263822,"question":"What is your skill level as a developer? (Everyone is welcome in GDG, just like to get an idea)","answer":"Novice"},{"question_id":3263832,"question":"What are the 3 Tags that characterise you? ","answer":"Ideas\r\nSimplicity\r\nSolutions"}],"intro":"Founder of Yappp","link":"https://www.meetup.com/GDG-Budapest/members/46033482/"},"is_pro_admin":false},{"id":109038802,"name":"Kocsis F.","status":"active","joined":1377869624000,"city":"Budapest","country":"hu","localized_country_name":"Hungary","lat":47.51,"lon":19.08,"photo":{"id":146812662,"photo_link":"https://secure.meetupstatic.com/photos/member/c/d/b/6/member_146812662.jpeg","thumb_link":"https://secure.meetupstatic.com/photos/member/c/d/b/6/thumb_146812662.jpeg","type":"member","base_url":"https://secure.meetupstatic.com"},"group_profile":{"status":"active","visited":1532950987000,"created":1379954131000,"updated":1502110308000,"role":"coorganizer","group":{"id":6397942,"urlname":"GDG-Budapest","name":"GDG Budapest","status":"active","who":"GDG Budapester","members":1203,"join_mode":"open","localized_location":"Budapest, Hungary"},"answers":[{"question_id":3263842,"question":"What Google technologies are you using?","answer":"Analytics, Drive, G+, Adwords, Webmaster tools, Trends, Cloud, ..."},{"question_id":3263822,"question":"What is your skill level as a developer? (Everyone is welcome in GDG, just like to get an idea)","answer":"Idea validation, development management"},{"question_id":3263832,"question":"What are the 3 Tags that characterise you? ","answer":"challenge\r\nexplore\r\nmanage"}],"intro":"G.M. Production CEO","link":"https://www.meetup.com/GDG-Budapest/members/109038802/"},"is_pro_admin":false},{"id":204543692,"name":"Péter E.","status":"active","joined":1462389674000,"city":"Budapest","country":"hu","localized_country_name":"Hungary","lat":47.51,"lon":19.08,"photo":{"id":256255028,"highres_link":"https://secure.meetupstatic.com/photos/member/d/6/f/4/highres_256255028.jpeg","photo_link":"https://secure.meetupstatic.com/photos/member/d/6/f/4/member_256255028.jpeg","thumb_link":"https://secure.meetupstatic.com/photos/member/d/6/f/4/thumb_256255028.jpeg","type":"member","base_url":"https://secure.meetupstatic.com"},"group_profile":{"status":"active","visited":1554795989000,"created":1462389781000,"updated":1553261420000,"role":"coorganizer","group":{"id":6397942,"urlname":"GDG-Budapest","name":"GDG Budapest","status":"active","who":"GDG Budapester","members":1203,"join_mode":"open","localized_location":"Budapest, Hungary"},"answers":[{"question_id":3263842,"question":"What Google technologies are you using?","answer":"Android, Web"},{"question_id":3263822,"question":"What is your skill level as a developer? (Everyone is welcome in GDG, just like to get an idea)","answer":"8/10"},{"question_id":3263832,"question":"What are the 3 Tags that characterise you? ","answer":"innovative, agile, demanding"}],"link":"https://www.meetup.com/GDG-Budapest/members/204543692/"},"is_pro_admin":false},{"id":267264020,"name":"Zsigmond P. T.","status":"active","joined":1541587788000,"city":"Budapest","country":"hu","localized_country_name":"Hungary","lat":47.51,"lon":19.08,"photo":{"id":282208249,"highres_link":"https://secure.meetupstatic.com/photos/member/6/e/5/9/highres_282208249.jpeg","photo_link":"https://secure.meetupstatic.com/photos/member/6/e/5/9/member_282208249.jpeg","thumb_link":"https://secure.meetupstatic.com/photos/member/6/e/5/9/thumb_282208249.jpeg","type":"member","base_url":"https://secure.meetupstatic.com"},"group_profile":{"status":"active","visited":1553694921000,"created":1542921488000,"updated":1549919286000,"role":"coorganizer","group":{"id":6397942,"urlname":"GDG-Budapest","name":"GDG Budapest","status":"active","who":"GDG Budapester","members":1203,"join_mode":"open","localized_location":"Budapest, Hungary"},"answers":[{"question_id":3263842,"question":"What Google technologies are you using?","answer":"GCP, GSuite, GMail"},{"question_id":3263822,"question":"What is your skill level as a developer? (Everyone is welcome in GDG, just like to get an idea)","answer":"Chuck Norris"},{"question_id":3263832,"question":"What are the 3 Tags that characterise you? ","answer":"dreamer, inventor, pioneer"}],"link":"https://www.meetup.com/GDG-Budapest/members/267264020/"},"is_pro_admin":false}]}
